<?xml version="1.0" ?>
<tv date="20260225105537 +0800">
	<channel id="CCTV-1">
		<display-name lang="zh">CCTV-1</display-name>
	</channel>
	<channel id="CCTV-10">
		<display-name lang="zh">CCTV-10</display-name>
	</channel>
	<channel id="CCTV-11">
		<display-name lang="zh">CCTV-11</display-name>
	</channel>
	<channel id="CCTV-12">
		<display-name lang="zh">CCTV-12</display-name>
	</channel>
	<channel id="CCTV-13">
		<display-name lang="zh">CCTV-13</display-name>
	</channel>
	<channel id="CCTV-14">
		<display-name lang="zh">CCTV-14</display-name>
	</channel>
	<channel id="CCTV-15">
		<display-name lang="zh">CCTV-15</display-name>
	</channel>
	<channel id="CCTV-16">
		<display-name lang="zh">CCTV-16</display-name>
	</channel>
	<channel id="CCTV-17">
		<display-name lang="zh">CCTV-17</display-name>
	</channel>
	<channel id="CCTV-2">
		<display-name lang="zh">CCTV-2</display-name>
	</channel>
	<channel id="CCTV-3">
		<display-name lang="zh">CCTV-3</display-name>
	</channel>
	<channel id="CCTV-4">
		<display-name lang="zh">CCTV-4</display-name>
	</channel>
	<channel id="CCTV-5">
		<display-name lang="zh">CCTV-5</display-name>
	</channel>
	<channel id="CCTV-5+">
		<display-name lang="zh">CCTV-5+</display-name>
	</channel>
	<channel id="CCTV-6">
		<display-name lang="zh">CCTV-6</display-name>
	</channel>
	<channel id="CCTV-7">
		<display-name lang="zh">CCTV-7</display-name>
	</channel>
	<channel id="CCTV-8">
		<display-name lang="zh">CCTV-8</display-name>
	</channel>
	<channel id="CCTV-9">
		<display-name lang="zh">CCTV-9</display-name>
	</channel>
	<channel id="怀旧剧场">
		<display-name lang="zh">怀旧剧场</display-name>
	</channel>
	<channel id="第一剧场">
		<display-name lang="zh">第一剧场</display-name>
	</channel>
	<channel id="风云剧场">
		<display-name lang="zh">风云剧场</display-name>
	</channel>
	<channel id="CHC动作电影">
		<display-name lang="zh">CHC动作电影</display-name>
	</channel>
	<channel id="CHC家庭影院">
		<display-name lang="zh">CHC家庭影院</display-name>
	</channel>
	<channel id="CHC高清电影">
		<display-name lang="zh">CHC高清电影</display-name>
	</channel>
	<channel id="三沙卫视">
		<display-name lang="zh">三沙卫视</display-name>
	</channel>
	<channel id="上海新闻综合">
		<display-name lang="zh">上海新闻综合</display-name>
	</channel>
	<channel id="上海第一财经">
		<display-name lang="zh">上海第一财经</display-name>
	</channel>
	<channel id="上海都市">
		<display-name lang="zh">上海都市</display-name>
	</channel>
	<channel id="东南卫视">
		<display-name lang="zh">东南卫视</display-name>
	</channel>
	<channel id="东方卫视">
		<display-name lang="zh">东方卫视</display-name>
	</channel>
	<channel id="CETV-2">
		<display-name lang="zh">CETV-2</display-name>
	</channel>
	<channel id="CETV-4">
		<display-name lang="zh">CETV-4</display-name>
	</channel>
	<channel id="云南卫视">
		<display-name lang="zh">云南卫视</display-name>
	</channel>
	<channel id="佛山综合">
		<display-name lang="zh">佛山综合</display-name>
	</channel>
	<channel id="内蒙古农牧">
		<display-name lang="zh">内蒙古农牧</display-name>
	</channel>
	<channel id="内蒙古卫视">
		<display-name lang="zh">内蒙古卫视</display-name>
	</channel>
	<channel id="内蒙古少儿">
		<display-name lang="zh">内蒙古少儿</display-name>
	</channel>
	<channel id="内蒙古综合">
		<display-name lang="zh">内蒙古综合</display-name>
	</channel>
	<channel id="动漫秀场">
		<display-name lang="zh">动漫秀场</display-name>
	</channel>
	<channel id="劲爆体育">
		<display-name lang="zh">劲爆体育</display-name>
	</channel>
	<channel id="北京卫视">
		<display-name lang="zh">北京卫视</display-name>
	</channel>
	<channel id="北京新闻">
		<display-name lang="zh">北京新闻</display-name>
	</channel>
	<channel id="北京生活">
		<display-name lang="zh">北京生活</display-name>
	</channel>
	<channel id="北京财经">
		<display-name lang="zh">北京财经</display-name>
	</channel>
	<channel id="北海新闻综合">
		<display-name lang="zh">北海新闻综合</display-name>
	</channel>
	<channel id="北海经济科教">
		<display-name lang="zh">北海经济科教</display-name>
	</channel>
	<channel id="南京信息">
		<display-name lang="zh">南京信息</display-name>
	</channel>
	<channel id="南京十八">
		<display-name lang="zh">南京十八</display-name>
	</channel>
	<channel id="南京少儿">
		<display-name lang="zh">南京少儿</display-name>
	</channel>
	<channel id="南京教科">
		<display-name lang="zh">南京教科</display-name>
	</channel>
	<channel id="南京新闻综合">
		<display-name lang="zh">南京新闻综合</display-name>
	</channel>
	<channel id="北京卡酷少儿">
		<display-name lang="zh">北京卡酷少儿</display-name>
	</channel>
	<channel id="厦门卫视">
		<display-name lang="zh">厦门卫视</display-name>
	</channel>
	<channel id="吉林乡村">
		<display-name lang="zh">吉林乡村</display-name>
	</channel>
	<channel id="吉林卫视">
		<display-name lang="zh">吉林卫视</display-name>
	</channel>
	<channel id="吉林生活">
		<display-name lang="zh">吉林生活</display-name>
	</channel>
	<channel id="吉林都市">
		<display-name lang="zh">吉林都市</display-name>
	</channel>
	<channel id="四川卫视">
		<display-name lang="zh">四川卫视</display-name>
	</channel>
	<channel id="大湾区卫视">
		<display-name lang="zh">大湾区卫视</display-name>
	</channel>
	<channel id="天津体育">
		<display-name lang="zh">天津体育</display-name>
	</channel>
	<channel id="天津卫视">
		<display-name lang="zh">天津卫视</display-name>
	</channel>
	<channel id="天津文艺">
		<display-name lang="zh">天津文艺</display-name>
	</channel>
	<channel id="天津新闻">
		<display-name lang="zh">天津新闻</display-name>
	</channel>
	<channel id="天津都市">
		<display-name lang="zh">天津都市</display-name>
	</channel>
	<channel id="宁夏公共">
		<display-name lang="zh">宁夏公共</display-name>
	</channel>
	<channel id="宁夏卫视">
		<display-name lang="zh">宁夏卫视</display-name>
	</channel>
	<channel id="宁夏少儿">
		<display-name lang="zh">宁夏少儿</display-name>
	</channel>
	<channel id="宁夏经济">
		<display-name lang="zh">宁夏经济</display-name>
	</channel>
	<channel id="安徽卫视">
		<display-name lang="zh">安徽卫视</display-name>
	</channel>
	<channel id="安徽影视">
		<display-name lang="zh">安徽影视</display-name>
	</channel>
	<channel id="安徽经济生活">
		<display-name lang="zh">安徽经济生活</display-name>
	</channel>
	<channel id="安徽综艺体育">
		<display-name lang="zh">安徽综艺体育</display-name>
	</channel>
	<channel id="宜宾新闻综合">
		<display-name lang="zh">宜宾新闻综合</display-name>
	</channel>
	<channel id="山东农科">
		<display-name lang="zh">山东农科</display-name>
	</channel>
	<channel id="山东卫视">
		<display-name lang="zh">山东卫视</display-name>
	</channel>
	<channel id="山东教育">
		<display-name lang="zh">山东教育</display-name>
	</channel>
	<channel id="山东生活">
		<display-name lang="zh">山东生活</display-name>
	</channel>
	<channel id="山东综艺">
		<display-name lang="zh">山东综艺</display-name>
	</channel>
	<channel id="山东齐鲁">
		<display-name lang="zh">山东齐鲁</display-name>
	</channel>
	<channel id="山西卫视">
		<display-name lang="zh">山西卫视</display-name>
	</channel>
	<channel id="山西影视">
		<display-name lang="zh">山西影视</display-name>
	</channel>
	<channel id="山西文体生活">
		<display-name lang="zh">山西文体生活</display-name>
	</channel>
	<channel id="山西社会与法治">
		<display-name lang="zh">山西社会与法治</display-name>
	</channel>
	<channel id="山西经济">
		<display-name lang="zh">山西经济</display-name>
	</channel>
	<channel id="广东卫视">
		<display-name lang="zh">广东卫视</display-name>
	</channel>
	<channel id="广东新闻">
		<display-name lang="zh">广东新闻</display-name>
	</channel>
	<channel id="广东珠江">
		<display-name lang="zh">广东珠江</display-name>
	</channel>
	<channel id="广州竞赛">
		<display-name lang="zh">广州竞赛</display-name>
	</channel>
	<channel id="广西卫视">
		<display-name lang="zh">广西卫视</display-name>
	</channel>
	<channel id="广西国际">
		<display-name lang="zh">广西国际</display-name>
	</channel>
	<channel id="广西新闻">
		<display-name lang="zh">广西新闻</display-name>
	</channel>
	<channel id="康巴卫视">
		<display-name lang="zh">康巴卫视</display-name>
	</channel>
	<channel id="延边卫视">
		<display-name lang="zh">延边卫视</display-name>
	</channel>
	<channel id="快乐垂钓">
		<display-name lang="zh">快乐垂钓</display-name>
	</channel>
	<channel id="攀枝花新闻综合">
		<display-name lang="zh">攀枝花新闻综合</display-name>
	</channel>
	<channel id="新疆卫视">
		<display-name lang="zh">新疆卫视</display-name>
	</channel>
	<channel id="无锡娱乐">
		<display-name lang="zh">无锡娱乐</display-name>
	</channel>
	<channel id="无锡生活">
		<display-name lang="zh">无锡生活</display-name>
	</channel>
	<channel id="无锡经济">
		<display-name lang="zh">无锡经济</display-name>
	</channel>
	<channel id="日照科教">
		<display-name lang="zh">日照科教</display-name>
	</channel>
	<channel id="杭州导视">
		<display-name lang="zh">杭州导视</display-name>
	</channel>
	<channel id="杭州影视">
		<display-name lang="zh">杭州影视</display-name>
	</channel>
	<channel id="杭州生活">
		<display-name lang="zh">杭州生活</display-name>
	</channel>
	<channel id="杭州综合">
		<display-name lang="zh">杭州综合</display-name>
	</channel>
	<channel id="杭州西湖明珠">
		<display-name lang="zh">杭州西湖明珠</display-name>
	</channel>
	<channel id="梨园">
		<display-name lang="zh">梨园</display-name>
	</channel>
	<channel id="欢笑剧场">
		<display-name lang="zh">欢笑剧场</display-name>
	</channel>
	<channel id="汕头综合">
		<display-name lang="zh">汕头综合</display-name>
	</channel>
	<channel id="优漫卡通">
		<display-name lang="zh">优漫卡通</display-name>
	</channel>
	<channel id="江苏卫视">
		<display-name lang="zh">江苏卫视</display-name>
	</channel>
	<channel id="江苏城市">
		<display-name lang="zh">江苏城市</display-name>
	</channel>
	<channel id="江苏影视">
		<display-name lang="zh">江苏影视</display-name>
	</channel>
	<channel id="江西卫视">
		<display-name lang="zh">江西卫视</display-name>
	</channel>
	<channel id="江门综合">
		<display-name lang="zh">江门综合</display-name>
	</channel>
	<channel id="河北农民">
		<display-name lang="zh">河北农民</display-name>
	</channel>
	<channel id="河北卫视">
		<display-name lang="zh">河北卫视</display-name>
	</channel>
	<channel id="河北少儿科教">
		<display-name lang="zh">河北少儿科教</display-name>
	</channel>
	<channel id="河北都市">
		<display-name lang="zh">河北都市</display-name>
	</channel>
	<channel id="河南卫视">
		<display-name lang="zh">河南卫视</display-name>
	</channel>
	<channel id="河南民生">
		<display-name lang="zh">河南民生</display-name>
	</channel>
	<channel id="河南都市">
		<display-name lang="zh">河南都市</display-name>
	</channel>
	<channel id="法治天地">
		<display-name lang="zh">法治天地</display-name>
	</channel>
	<channel id="浙江公共新闻">
		<display-name lang="zh">浙江公共新闻</display-name>
	</channel>
	<channel id="浙江卫视">
		<display-name lang="zh">浙江卫视</display-name>
	</channel>
	<channel id="浙江国际">
		<display-name lang="zh">浙江国际</display-name>
	</channel>
	<channel id="浙江少儿">
		<display-name lang="zh">浙江少儿</display-name>
	</channel>
	<channel id="浙江教科影视">
		<display-name lang="zh">浙江教科影视</display-name>
	</channel>
	<channel id="浙江教育">
		<display-name lang="zh">浙江教育</display-name>
	</channel>
	<channel id="浙江数码时代">
		<display-name lang="zh">浙江数码时代</display-name>
	</channel>
	<channel id="浙江民生">
		<display-name lang="zh">浙江民生</display-name>
	</channel>
	<channel id="浙江民生休闲">
		<display-name lang="zh">浙江民生休闲</display-name>
	</channel>
	<channel id="浙江经济生活">
		<display-name lang="zh">浙江经济生活</display-name>
	</channel>
	<channel id="浙江经视">
		<display-name lang="zh">浙江经视</display-name>
	</channel>
	<channel id="浙江钱江都市">
		<display-name lang="zh">浙江钱江都市</display-name>
	</channel>
	<channel id="海南公共">
		<display-name lang="zh">海南公共</display-name>
	</channel>
	<channel id="海南卫视">
		<display-name lang="zh">海南卫视</display-name>
	</channel>
	<channel id="海南少儿">
		<display-name lang="zh">海南少儿</display-name>
	</channel>
	<channel id="海南文旅">
		<display-name lang="zh">海南文旅</display-name>
	</channel>
	<channel id="海南新闻">
		<display-name lang="zh">海南新闻</display-name>
	</channel>
	<channel id="海南自贸">
		<display-name lang="zh">海南自贸</display-name>
	</channel>
	<channel id="深圳卫视">
		<display-name lang="zh">深圳卫视</display-name>
	</channel>
	<channel id="游戏风云">
		<display-name lang="zh">游戏风云</display-name>
	</channel>
	<channel id="湖北卫视">
		<display-name lang="zh">湖北卫视</display-name>
	</channel>
	<channel id="湖南卫视">
		<display-name lang="zh">湖南卫视</display-name>
	</channel>
	<channel id="湖南国际">
		<display-name lang="zh">湖南国际</display-name>
	</channel>
	<channel id="湖南娱乐">
		<display-name lang="zh">湖南娱乐</display-name>
	</channel>
	<channel id="湖南爱晚">
		<display-name lang="zh">湖南爱晚</display-name>
	</channel>
	<channel id="湖南电影">
		<display-name lang="zh">湖南电影</display-name>
	</channel>
	<channel id="湖南电视剧">
		<display-name lang="zh">湖南电视剧</display-name>
	</channel>
	<channel id="湖南经视">
		<display-name lang="zh">湖南经视</display-name>
	</channel>
	<channel id="漳州新闻">
		<display-name lang="zh">漳州新闻</display-name>
	</channel>
	<channel id="甘肃公共">
		<display-name lang="zh">甘肃公共</display-name>
	</channel>
	<channel id="甘肃卫视">
		<display-name lang="zh">甘肃卫视</display-name>
	</channel>
	<channel id="甘肃少儿">
		<display-name lang="zh">甘肃少儿</display-name>
	</channel>
	<channel id="生活时尚">
		<display-name lang="zh">生活时尚</display-name>
	</channel>
	<channel id="电视指南">
		<display-name lang="zh">电视指南</display-name>
	</channel>
	<channel id="睛彩篮球">
		<display-name lang="zh">睛彩篮球</display-name>
	</channel>
	<channel id="睛彩羽毛球">
		<display-name lang="zh">睛彩羽毛球</display-name>
	</channel>
	<channel id="石家庄娱乐">
		<display-name lang="zh">石家庄娱乐</display-name>
	</channel>
	<channel id="石家庄新闻综合">
		<display-name lang="zh">石家庄新闻综合</display-name>
	</channel>
	<channel id="石家庄生活">
		<display-name lang="zh">石家庄生活</display-name>
	</channel>
	<channel id="石家庄都市">
		<display-name lang="zh">石家庄都市</display-name>
	</channel>
	<channel id="福建文体">
		<display-name lang="zh">福建文体</display-name>
	</channel>
	<channel id="福建少儿">
		<display-name lang="zh">福建少儿</display-name>
	</channel>
	<channel id="福建新闻">
		<display-name lang="zh">福建新闻</display-name>
	</channel>
	<channel id="福建旅游">
		<display-name lang="zh">福建旅游</display-name>
	</channel>
	<channel id="福建电视剧">
		<display-name lang="zh">福建电视剧</display-name>
	</channel>
	<channel id="福建经济">
		<display-name lang="zh">福建经济</display-name>
	</channel>
	<channel id="福建综合">
		<display-name lang="zh">福建综合</display-name>
	</channel>
	<channel id="第一财经">
		<display-name lang="zh">第一财经</display-name>
	</channel>
	<channel id="翡翠台">
		<display-name lang="zh">翡翠台</display-name>
	</channel>
	<channel id="苏州新闻综合">
		<display-name lang="zh">苏州新闻综合</display-name>
	</channel>
	<channel id="茂名公共">
		<display-name lang="zh">茂名公共</display-name>
	</channel>
	<channel id="茂名综合">
		<display-name lang="zh">茂名综合</display-name>
	</channel>
	<channel id="贵州卫视">
		<display-name lang="zh">贵州卫视</display-name>
	</channel>
	<channel id="辽宁卫视">
		<display-name lang="zh">辽宁卫视</display-name>
	</channel>
	<channel id="都市剧场">
		<display-name lang="zh">都市剧场</display-name>
	</channel>
	<channel id="重庆卫视">
		<display-name lang="zh">重庆卫视</display-name>
	</channel>
	<channel id="重庆新闻">
		<display-name lang="zh">重庆新闻</display-name>
	</channel>
	<channel id="银川公共">
		<display-name lang="zh">银川公共</display-name>
	</channel>
	<channel id="银川文体">
		<display-name lang="zh">银川文体</display-name>
	</channel>
	<channel id="银川生活">
		<display-name lang="zh">银川生活</display-name>
	</channel>
	<channel id="长沙影视">
		<display-name lang="zh">长沙影视</display-name>
	</channel>
	<channel id="长沙政法">
		<display-name lang="zh">长沙政法</display-name>
	</channel>
	<channel id="陕西农林卫视">
		<display-name lang="zh">陕西农林卫视</display-name>
	</channel>
	<channel id="陕西卫视">
		<display-name lang="zh">陕西卫视</display-name>
	</channel>
	<channel id="陕西影视">
		<display-name lang="zh">陕西影视</display-name>
	</channel>
	<channel id="青海卫视">
		<display-name lang="zh">青海卫视</display-name>
	</channel>
	<channel id="青海经视">
		<display-name lang="zh">青海经视</display-name>
	</channel>
	<channel id="青海都市">
		<display-name lang="zh">青海都市</display-name>
	</channel>
	<channel id="高尔夫网球">
		<display-name lang="zh">高尔夫网球</display-name>
	</channel>
	<channel id="魅力足球">
		<display-name lang="zh">魅力足球</display-name>
	</channel>
	<channel id="黑龙江卫视">
		<display-name lang="zh">黑龙江卫视</display-name>
	</channel>
	<channel id="黑龙江少儿">
		<display-name lang="zh">黑龙江少儿</display-name>
	</channel>
	<channel id="黑龙江影视">
		<display-name lang="zh">黑龙江影视</display-name>
	</channel>
	<channel id="黑龙江文体">
		<display-name lang="zh">黑龙江文体</display-name>
	</channel>
	<channel id="黑龙江新闻法治">
		<display-name lang="zh">黑龙江新闻法治</display-name>
	</channel>
	<channel id="黑龙江都市">
		<display-name lang="zh">黑龙江都市</display-name>
	</channel>
	<channel id="NewTV动作电影">
		<display-name lang="zh">NewTV动作电影</display-name>
	</channel>
	<channel id="NewTV惊悚悬疑">
		<display-name lang="zh">NewTV惊悚悬疑</display-name>
	</channel>
	<channel id="西藏卫视">
		<display-name lang="zh">西藏卫视</display-name>
	</channel>
	<channel id="世界地理">
		<display-name lang="zh">世界地理</display-name>
	</channel>
	<channel id="央视台球">
		<display-name lang="zh">央视台球</display-name>
	</channel>
	<channel id="文化精品">
		<display-name lang="zh">文化精品</display-name>
	</channel>
	<channel id="女性时尚">
		<display-name lang="zh">女性时尚</display-name>
	</channel>
	<channel id="风云足球">
		<display-name lang="zh">风云足球</display-name>
	</channel>
	<channel id="风云音乐">
		<display-name lang="zh">风云音乐</display-name>
	</channel>
	<channel id="天元围棋">
		<display-name lang="zh">天元围棋</display-name>
	</channel>
	<channel id="游戏竞技">
		<display-name lang="zh">游戏竞技</display-name>
	</channel>
	<channel id="BTV纪实">
		<display-name lang="zh">BTV纪实</display-name>
	</channel>
	<channel id="滨海新闻综合">
		<display-name lang="zh">滨海新闻综合</display-name>
	</channel>
	<channel id="CETV-1">
		<display-name lang="zh">CETV-1</display-name>
	</channel>
	<channel id="CETV-3">
		<display-name lang="zh">CETV-3</display-name>
	</channel>
	<channel id="哈哈炫动">
		<display-name lang="zh">哈哈炫动</display-name>
	</channel>
	<programme channel="哈哈炫动" start="20260225001500 +0800" stop="20260225024200 +0800">
		<title lang="zh">动画片剧场</title>
	</programme>
	<programme channel="哈哈炫动" start="20260225024200 +0800" stop="20260225060000 +0800">
		<title lang="zh">动画片剧场</title>
	</programme>
	<programme channel="哈哈炫动" start="20260225060000 +0800" stop="20260225071500 +0800">
		<title lang="zh">动画片剧场</title>
	</programme>
	<programme channel="哈哈炫动" start="20260225071500 +0800" stop="20260225073000 +0800">
		<title lang="zh">炫动酷地带</title>
	</programme>
	<programme channel="哈哈炫动" start="20260225073000 +0800" stop="20260225080000 +0800">
		<title lang="zh">欢乐蹦蹦跳</title>
	</programme>
	<programme channel="哈哈炫动" start="20260225080000 +0800" stop="20260225120000 +0800">
		<title lang="zh">动画片剧场</title>
	</programme>
	<programme channel="哈哈炫动" start="20260225120000 +0800" stop="20260225121500 +0800">
		<title lang="zh">炫动酷地带</title>
	</programme>
	<programme channel="哈哈炫动" start="20260225121500 +0800" stop="20260225123000 +0800">
		<title lang="zh">新闻同学</title>
	</programme>
	<programme channel="哈哈炫动" start="20260225123000 +0800" stop="20260225133000 +0800">
		<title lang="zh">动画片剧场</title>
	</programme>
	<programme channel="哈哈炫动" start="20260225133000 +0800" stop="20260225163000 +0800">
		<title lang="zh">动画片剧场</title>
	</programme>
	<programme channel="哈哈炫动" start="20260225163000 +0800" stop="20260225170000 +0800">
		<title lang="zh">动画片剧场</title>
	</programme>
	<programme channel="哈哈炫动" start="20260225170000 +0800" stop="20260225180000 +0800">
		<title lang="zh">动画片剧场</title>
	</programme>
	<programme channel="哈哈炫动" start="20260225180000 +0800" stop="20260225190000 +0800">
		<title lang="zh">动画片剧场</title>
	</programme>
	<programme channel="哈哈炫动" start="20260225190000 +0800" stop="20260225191500 +0800">
		<title lang="zh">新闻同学</title>
	</programme>
	<programme channel="哈哈炫动" start="20260225191500 +0800" stop="20260225193000 +0800">
		<title lang="zh">荧星梦工厂</title>
	</programme>
	<programme channel="哈哈炫动" start="20260225193000 +0800" stop="20260225203000 +0800">
		<title lang="zh">动画片剧场</title>
	</programme>
	<programme channel="哈哈炫动" start="20260225203000 +0800" stop="20260225220000 +0800">
		<title lang="zh">动画片剧场</title>
	</programme>
	<programme channel="哈哈炫动" start="20260225220000 +0800" stop="20260225230000 +0800">
		<title lang="zh">动画片剧场</title>
	</programme>
	<programme channel="哈哈炫动" start="20260225230000 +0800" stop="20260225231500 +0800">
		<title lang="zh">新闻同学</title>
	</programme>
	<programme channel="哈哈炫动" start="20260225231500 +0800" stop="20260226001500 +0800">
		<title lang="zh">动画片剧场</title>
	</programme>
	<programme channel="哈哈炫动" start="20260226001500 +0800" stop="20260226024200 +0800">
		<title lang="zh">动画片剧场</title>
	</programme>
	<programme channel="哈哈炫动" start="20260226024200 +0800" stop="20260226060000 +0800">
		<title lang="zh">动画片剧场</title>
	</programme>
	<programme channel="哈哈炫动" start="20260226060000 +0800" stop="20260226071500 +0800">
		<title lang="zh">动画片剧场</title>
	</programme>
	<programme channel="哈哈炫动" start="20260226071500 +0800" stop="20260226073000 +0800">
		<title lang="zh">炫动酷地带</title>
	</programme>
	<programme channel="哈哈炫动" start="20260226073000 +0800" stop="20260226080000 +0800">
		<title lang="zh">欢乐蹦蹦跳</title>
	</programme>
	<programme channel="哈哈炫动" start="20260226080000 +0800" stop="20260226120000 +0800">
		<title lang="zh">动画片剧场</title>
	</programme>
	<programme channel="哈哈炫动" start="20260226120000 +0800" stop="20260226121500 +0800">
		<title lang="zh">炫动酷地带</title>
	</programme>
	<programme channel="哈哈炫动" start="20260226121500 +0800" stop="20260226123000 +0800">
		<title lang="zh">新闻同学</title>
	</programme>
	<programme channel="哈哈炫动" start="20260226123000 +0800" stop="20260226133000 +0800">
		<title lang="zh">动画片剧场</title>
	</programme>
	<programme channel="哈哈炫动" start="20260226133000 +0800" stop="20260226163000 +0800">
		<title lang="zh">动画片剧场</title>
	</programme>
	<programme channel="哈哈炫动" start="20260226163000 +0800" stop="20260226170000 +0800">
		<title lang="zh">动画片剧场</title>
	</programme>
	<programme channel="哈哈炫动" start="20260226170000 +0800" stop="20260226180000 +0800">
		<title lang="zh">动画片剧场</title>
	</programme>
	<programme channel="哈哈炫动" start="20260226180000 +0800" stop="20260226190000 +0800">
		<title lang="zh">动画片剧场</title>
	</programme>
	<programme channel="哈哈炫动" start="20260226190000 +0800" stop="20260226191500 +0800">
		<title lang="zh">新闻同学</title>
	</programme>
	<programme channel="哈哈炫动" start="20260226191500 +0800" stop="20260226193000 +0800">
		<title lang="zh">荧星梦工厂</title>
	</programme>
	<programme channel="哈哈炫动" start="20260226193000 +0800" stop="20260226203000 +0800">
		<title lang="zh">动画片剧场</title>
	</programme>
	<programme channel="哈哈炫动" start="20260226203000 +0800" stop="20260226220000 +0800">
		<title lang="zh">动画片剧场</title>
	</programme>
	<programme channel="哈哈炫动" start="20260226220000 +0800" stop="20260226230000 +0800">
		<title lang="zh">动画片剧场</title>
	</programme>
	<programme channel="哈哈炫动" start="20260226230000 +0800" stop="20260226231500 +0800">
		<title lang="zh">新闻同学</title>
	</programme>
	<programme channel="哈哈炫动" start="20260226231500 +0800" stop="20260227001500 +0800">
		<title lang="zh">动画片剧场</title>
	</programme>
	<channel id="金鹰卡通">
		<display-name lang="zh">金鹰卡通</display-name>
	</channel>
	<programme channel="金鹰卡通" start="20260225000000 +0800" stop="20260225064500 +0800">
		<title lang="zh">熊出没之探险日记2</title>
	</programme>
	<programme channel="金鹰卡通" start="20260225064500 +0800" stop="20260225070000 +0800">
		<title lang="zh">麦咭小食光·盒你过大年(3)</title>
	</programme>
	<programme channel="金鹰卡通" start="20260225070000 +0800" stop="20260225071000 +0800">
		<title lang="zh">麦咭嗨唱会,麦咭安全启蒙</title>
	</programme>
	<programme channel="金鹰卡通" start="20260225071000 +0800" stop="20260225072000 +0800">
		<title lang="zh">熊熊帮帮团3(18)</title>
	</programme>
	<programme channel="金鹰卡通" start="20260225072000 +0800" stop="20260225073000 +0800">
		<title lang="zh">熊熊帮帮团3(19)</title>
	</programme>
	<programme channel="金鹰卡通" start="20260225073000 +0800" stop="20260225074000 +0800">
		<title lang="zh">熊熊帮帮团3(20)</title>
	</programme>
	<programme channel="金鹰卡通" start="20260225074000 +0800" stop="20260225075000 +0800">
		<title lang="zh">熊熊帮帮团3(21)</title>
	</programme>
	<programme channel="金鹰卡通" start="20260225075000 +0800" stop="20260225080000 +0800">
		<title lang="zh">熊熊帮帮团3(22)</title>
	</programme>
	<programme channel="金鹰卡通" start="20260225080000 +0800" stop="20260225081200 +0800">
		<title lang="zh">巴啦啦小魔仙之曜星守护者(16)</title>
	</programme>
	<programme channel="金鹰卡通" start="20260225081200 +0800" stop="20260225082400 +0800">
		<title lang="zh">巴啦啦小魔仙之曜星守护者(17)</title>
	</programme>
	<programme channel="金鹰卡通" start="20260225082400 +0800" stop="20260225083600 +0800">
		<title lang="zh">巴啦啦小魔仙之曜星守护者(18)</title>
	</programme>
	<programme channel="金鹰卡通" start="20260225083600 +0800" stop="20260225084800 +0800">
		<title lang="zh">巴啦啦小魔仙之曜星守护者(19)</title>
	</programme>
	<programme channel="金鹰卡通" start="20260225084800 +0800" stop="20260225090000 +0800">
		<title lang="zh">巴啦啦小魔仙之曜星守护者(20)</title>
	</programme>
	<programme channel="金鹰卡通" start="20260225090000 +0800" stop="20260225091100 +0800">
		<title lang="zh">熊出没之神奇宝物(31)</title>
	</programme>
	<programme channel="金鹰卡通" start="20260225091100 +0800" stop="20260225092200 +0800">
		<title lang="zh">熊出没之神奇宝物(32)</title>
	</programme>
	<programme channel="金鹰卡通" start="20260225092200 +0800" stop="20260225093300 +0800">
		<title lang="zh">熊出没之神奇宝物(33)</title>
	</programme>
	<programme channel="金鹰卡通" start="20260225093300 +0800" stop="20260225094500 +0800">
		<title lang="zh">熊出没之神奇宝物(34)</title>
	</programme>
	<programme channel="金鹰卡通" start="20260225094500 +0800" stop="20260225095600 +0800">
		<title lang="zh">熊出没之神奇宝物(35)</title>
	</programme>
	<programme channel="金鹰卡通" start="20260225095600 +0800" stop="20260225100700 +0800">
		<title lang="zh">熊出没之神奇宝物(36)</title>
	</programme>
	<programme channel="金鹰卡通" start="20260225100700 +0800" stop="20260225101800 +0800">
		<title lang="zh">熊出没之神奇宝物(37)</title>
	</programme>
	<programme channel="金鹰卡通" start="20260225101800 +0800" stop="20260225103000 +0800">
		<title lang="zh">熊出没之神奇宝物(38)</title>
	</programme>
	<programme channel="金鹰卡通" start="20260225103000 +0800" stop="20260225104100 +0800">
		<title lang="zh">熊出没之神奇宝物(39)</title>
	</programme>
	<programme channel="金鹰卡通" start="20260225104100 +0800" stop="20260225105200 +0800">
		<title lang="zh">熊出没之神奇宝物(40)</title>
	</programme>
	<programme channel="金鹰卡通" start="20260225105200 +0800" stop="20260225110300 +0800">
		<title lang="zh">熊出没之神奇宝物(41)</title>
	</programme>
	<programme channel="金鹰卡通" start="20260225110300 +0800" stop="20260225111500 +0800">
		<title lang="zh">熊出没之神奇宝物(42)</title>
	</programme>
	<programme channel="金鹰卡通" start="20260225111500 +0800" stop="20260225112600 +0800">
		<title lang="zh">熊出没之神奇宝物(43)</title>
	</programme>
	<programme channel="金鹰卡通" start="20260225112600 +0800" stop="20260225113700 +0800">
		<title lang="zh">熊出没之神奇宝物(44)</title>
	</programme>
	<programme channel="金鹰卡通" start="20260225113700 +0800" stop="20260225114800 +0800">
		<title lang="zh">熊出没之神奇宝物(45)</title>
	</programme>
	<programme channel="金鹰卡通" start="20260225114800 +0800" stop="20260225120000 +0800">
		<title lang="zh">熊出没之神奇宝物(46)</title>
	</programme>
	<programme channel="金鹰卡通" start="20260225120000 +0800" stop="20260225120300 +0800">
		<title lang="zh">新声时刻</title>
	</programme>
	<programme channel="金鹰卡通" start="20260225120300 +0800" stop="20260225130500 +0800">
		<title lang="zh">喜羊羊与灰太狼之古古怪界有古怪</title>
	</programme>
	<programme channel="金鹰卡通" start="20260225130500 +0800" stop="20260225135500 +0800">
		<title lang="zh">喜羊羊与灰太狼之古古怪界有古怪</title>
	</programme>
	<programme channel="金鹰卡通" start="20260225135500 +0800" stop="20260225140000 +0800">
		<title lang="zh">麦咭播报堂</title>
	</programme>
	<programme channel="金鹰卡通" start="20260225140000 +0800" stop="20260225141500 +0800">
		<title lang="zh">奇妙萌可之魔法钥匙(25)</title>
	</programme>
	<programme channel="金鹰卡通" start="20260225141500 +0800" stop="20260225143000 +0800">
		<title lang="zh">奇妙萌可之魔法钥匙(26)</title>
	</programme>
	<programme channel="金鹰卡通" start="20260225143000 +0800" stop="20260225162000 +0800">
		<title lang="zh">喜羊羊与灰太狼之异国破晓</title>
	</programme>
	<programme channel="金鹰卡通" start="20260225162000 +0800" stop="20260225162600 +0800">
		<title lang="zh">奶龙之奇妙冒险(38)</title>
	</programme>
	<programme channel="金鹰卡通" start="20260225162600 +0800" stop="20260225163300 +0800">
		<title lang="zh">奶龙之奇妙冒险(39)</title>
	</programme>
	<programme channel="金鹰卡通" start="20260225163300 +0800" stop="20260225164000 +0800">
		<title lang="zh">奶龙之奇妙冒险(40)</title>
	</programme>
	<programme channel="金鹰卡通" start="20260225164000 +0800" stop="20260225164600 +0800">
		<title lang="zh">奶龙搞怪大作战2(1)</title>
	</programme>
	<programme channel="金鹰卡通" start="20260225164600 +0800" stop="20260225165300 +0800">
		<title lang="zh">奶龙搞怪大作战2(2)</title>
	</programme>
	<programme channel="金鹰卡通" start="20260225165300 +0800" stop="20260225170000 +0800">
		<title lang="zh">奶龙搞怪大作战2(3)</title>
	</programme>
	<programme channel="金鹰卡通" start="20260225170000 +0800" stop="20260225172000 +0800">
		<title lang="zh">麦咭帮帮队</title>
	</programme>
	<programme channel="金鹰卡通" start="20260225172000 +0800" stop="20260225172800 +0800">
		<title lang="zh">奶龙搞怪大作战2(48)</title>
	</programme>
	<programme channel="金鹰卡通" start="20260225172800 +0800" stop="20260225173600 +0800">
		<title lang="zh">奶龙搞怪大作战2(49)</title>
	</programme>
	<programme channel="金鹰卡通" start="20260225173600 +0800" stop="20260225174400 +0800">
		<title lang="zh">奶龙搞怪大作战2(50)</title>
	</programme>
	<programme channel="金鹰卡通" start="20260225174400 +0800" stop="20260225175200 +0800">
		<title lang="zh">奶龙搞怪大作战2(51)</title>
	</programme>
	<programme channel="金鹰卡通" start="20260225175200 +0800" stop="20260225180000 +0800">
		<title lang="zh">奶龙搞怪大作战2(52)</title>
	</programme>
	<programme channel="金鹰卡通" start="20260225180000 +0800" stop="20260225181200 +0800">
		<title lang="zh">熊出没之探险日记2(1)</title>
	</programme>
	<programme channel="金鹰卡通" start="20260225181200 +0800" stop="20260225182400 +0800">
		<title lang="zh">熊出没之探险日记2(2)</title>
	</programme>
	<programme channel="金鹰卡通" start="20260225182400 +0800" stop="20260225183600 +0800">
		<title lang="zh">熊出没之探险日记2(3)</title>
	</programme>
	<programme channel="金鹰卡通" start="20260225183600 +0800" stop="20260225184800 +0800">
		<title lang="zh">熊出没之探险日记2(4)</title>
	</programme>
	<programme channel="金鹰卡通" start="20260225184800 +0800" stop="20260225190000 +0800">
		<title lang="zh">熊出没之探险日记2(5)</title>
	</programme>
	<programme channel="金鹰卡通" start="20260225190000 +0800" stop="20260225190300 +0800">
		<title lang="zh">新声时刻</title>
	</programme>
	<programme channel="金鹰卡通" start="20260225190300 +0800" stop="20260225191600 +0800">
		<title lang="zh">喜羊羊与灰太狼之奇侠大营救(20)</title>
	</programme>
	<programme channel="金鹰卡通" start="20260225191600 +0800" stop="20260225193000 +0800">
		<title lang="zh">喜羊羊与灰太狼之奇侠大营救(21)</title>
	</programme>
	<programme channel="金鹰卡通" start="20260225193000 +0800" stop="20260225194300 +0800">
		<title lang="zh">喜羊羊与灰太狼之奇侠大营救(22)</title>
	</programme>
	<programme channel="金鹰卡通" start="20260225194300 +0800" stop="20260225195700 +0800">
		<title lang="zh">喜羊羊与灰太狼之奇侠大营救(23)</title>
	</programme>
	<programme channel="金鹰卡通" start="20260225195700 +0800" stop="20260225201100 +0800">
		<title lang="zh">喜羊羊与灰太狼之奇侠大营救(24)</title>
	</programme>
	<programme channel="金鹰卡通" start="20260225201100 +0800" stop="20260225202400 +0800">
		<title lang="zh">喜羊羊与灰太狼之奇侠大营救(25)</title>
	</programme>
	<programme channel="金鹰卡通" start="20260225202400 +0800" stop="20260225203800 +0800">
		<title lang="zh">喜羊羊与灰太狼之奇侠大营救(26)</title>
	</programme>
	<programme channel="金鹰卡通" start="20260225203800 +0800" stop="20260225205100 +0800">
		<title lang="zh">喜羊羊与灰太狼之奇侠大营救(27)</title>
	</programme>
	<programme channel="金鹰卡通" start="20260225205100 +0800" stop="20260225210500 +0800">
		<title lang="zh">喜羊羊与灰太狼之奇侠大营救(28)</title>
	</programme>
	<programme channel="金鹰卡通" start="20260225210500 +0800" stop="20260225211900 +0800">
		<title lang="zh">喜羊羊与灰太狼之奇侠大营救(29)</title>
	</programme>
	<programme channel="金鹰卡通" start="20260225211900 +0800" stop="20260225213200 +0800">
		<title lang="zh">喜羊羊与灰太狼之奇侠大营救(30)</title>
	</programme>
	<programme channel="金鹰卡通" start="20260225213200 +0800" stop="20260225214600 +0800">
		<title lang="zh">喜羊羊与灰太狼之奇侠大营救(31)</title>
	</programme>
	<programme channel="金鹰卡通" start="20260225214600 +0800" stop="20260225220000 +0800">
		<title lang="zh">喜羊羊与灰太狼之奇侠大营救(32)</title>
	</programme>
	<programme channel="金鹰卡通" start="20260225220000 +0800" stop="20260225231000 +0800">
		<title lang="zh">中国新声代2026(2)</title>
	</programme>
	<programme channel="金鹰卡通" start="20260225231000 +0800" stop="20260225232000 +0800">
		<title lang="zh">熊出没之探险日记1(17)</title>
	</programme>
	<programme channel="金鹰卡通" start="20260225232000 +0800" stop="20260225233000 +0800">
		<title lang="zh">熊出没之探险日记1(18)</title>
	</programme>
	<programme channel="金鹰卡通" start="20260225233000 +0800" stop="20260225234000 +0800">
		<title lang="zh">熊出没之探险日记1(19)</title>
	</programme>
	<programme channel="金鹰卡通" start="20260225234000 +0800" stop="20260225235000 +0800">
		<title lang="zh">熊出没之探险日记1(20)</title>
	</programme>
	<programme channel="金鹰卡通" start="20260225235000 +0800" stop="20260225235900 +0800">
		<title lang="zh">熊出没之探险日记1(21)</title>
	</programme>
	<programme channel="金鹰卡通" start="20260225235900 +0800" stop="20260226000000 +0800">
		<title lang="zh">结束</title>
	</programme>
	<programme channel="金鹰卡通" start="20260226000000 +0800" stop="20260226064500 +0800">
		<title lang="zh">熊出没之神奇宝物</title>
	</programme>
	<programme channel="金鹰卡通" start="20260226064500 +0800" stop="20260226070000 +0800">
		<title lang="zh">麦咭小食光·盒你过大年(4)</title>
	</programme>
	<programme channel="金鹰卡通" start="20260226070000 +0800" stop="20260226071000 +0800">
		<title lang="zh">麦咭嗨唱会,麦咭安全启蒙</title>
	</programme>
	<programme channel="金鹰卡通" start="20260226071000 +0800" stop="20260226072000 +0800">
		<title lang="zh">熊熊帮帮团3(22)</title>
	</programme>
	<programme channel="金鹰卡通" start="20260226072000 +0800" stop="20260226073000 +0800">
		<title lang="zh">熊熊帮帮团3(23)</title>
	</programme>
	<programme channel="金鹰卡通" start="20260226073000 +0800" stop="20260226074000 +0800">
		<title lang="zh">熊熊帮帮团3(24)</title>
	</programme>
	<programme channel="金鹰卡通" start="20260226074000 +0800" stop="20260226075000 +0800">
		<title lang="zh">熊熊帮帮团3(25)</title>
	</programme>
	<programme channel="金鹰卡通" start="20260226075000 +0800" stop="20260226080000 +0800">
		<title lang="zh">熊熊帮帮团3(26)</title>
	</programme>
	<programme channel="金鹰卡通" start="20260226080000 +0800" stop="20260226081100 +0800">
		<title lang="zh">巴啦啦小魔仙之曜星守护者(21)</title>
	</programme>
	<programme channel="金鹰卡通" start="20260226081100 +0800" stop="20260226082300 +0800">
		<title lang="zh">巴啦啦小魔仙之曜星守护者(22)</title>
	</programme>
	<programme channel="金鹰卡通" start="20260226082300 +0800" stop="20260226083500 +0800">
		<title lang="zh">巴啦啦小魔仙之曜星守护者(23)</title>
	</programme>
	<programme channel="金鹰卡通" start="20260226083500 +0800" stop="20260226084600 +0800">
		<title lang="zh">巴啦啦小魔仙之曜星守护者(24)</title>
	</programme>
	<programme channel="金鹰卡通" start="20260226084600 +0800" stop="20260226085800 +0800">
		<title lang="zh">巴啦啦小魔仙之曜星守护者(25)</title>
	</programme>
	<programme channel="金鹰卡通" start="20260226085800 +0800" stop="20260226091000 +0800">
		<title lang="zh">巴啦啦小魔仙之曜星守护者(26)</title>
	</programme>
	<programme channel="金鹰卡通" start="20260226091000 +0800" stop="20260226092100 +0800">
		<title lang="zh">熊出没之神奇宝物(46)</title>
	</programme>
	<programme channel="金鹰卡通" start="20260226092100 +0800" stop="20260226093200 +0800">
		<title lang="zh">熊出没之神奇宝物(47)</title>
	</programme>
	<programme channel="金鹰卡通" start="20260226093200 +0800" stop="20260226094400 +0800">
		<title lang="zh">熊出没之神奇宝物(48)</title>
	</programme>
	<programme channel="金鹰卡通" start="20260226094400 +0800" stop="20260226095500 +0800">
		<title lang="zh">熊出没之神奇宝物(49)</title>
	</programme>
	<programme channel="金鹰卡通" start="20260226095500 +0800" stop="20260226100600 +0800">
		<title lang="zh">熊出没之神奇宝物(50)</title>
	</programme>
	<programme channel="金鹰卡通" start="20260226100600 +0800" stop="20260226101800 +0800">
		<title lang="zh">熊出没之神奇宝物(51)</title>
	</programme>
	<programme channel="金鹰卡通" start="20260226101800 +0800" stop="20260226102900 +0800">
		<title lang="zh">熊出没之神奇宝物(52)</title>
	</programme>
	<programme channel="金鹰卡通" start="20260226102900 +0800" stop="20260226104000 +0800">
		<title lang="zh">熊出没之神奇宝物(1)</title>
	</programme>
	<programme channel="金鹰卡通" start="20260226104000 +0800" stop="20260226105200 +0800">
		<title lang="zh">熊出没之神奇宝物(2)</title>
	</programme>
	<programme channel="金鹰卡通" start="20260226105200 +0800" stop="20260226110300 +0800">
		<title lang="zh">熊出没之神奇宝物(3)</title>
	</programme>
	<programme channel="金鹰卡通" start="20260226110300 +0800" stop="20260226111400 +0800">
		<title lang="zh">熊出没之神奇宝物(4)</title>
	</programme>
	<programme channel="金鹰卡通" start="20260226111400 +0800" stop="20260226112600 +0800">
		<title lang="zh">熊出没之神奇宝物(5)</title>
	</programme>
	<programme channel="金鹰卡通" start="20260226112600 +0800" stop="20260226113700 +0800">
		<title lang="zh">熊出没之神奇宝物(6)</title>
	</programme>
	<programme channel="金鹰卡通" start="20260226113700 +0800" stop="20260226114800 +0800">
		<title lang="zh">熊出没之神奇宝物(7)</title>
	</programme>
	<programme channel="金鹰卡通" start="20260226114800 +0800" stop="20260226120000 +0800">
		<title lang="zh">熊出没之神奇宝物(8)</title>
	</programme>
	<programme channel="金鹰卡通" start="20260226120000 +0800" stop="20260226120300 +0800">
		<title lang="zh">新声时刻</title>
	</programme>
	<programme channel="金鹰卡通" start="20260226120300 +0800" stop="20260226130500 +0800">
		<title lang="zh">喜羊羊与灰太狼之古古怪界有古怪</title>
	</programme>
	<programme channel="金鹰卡通" start="20260226130500 +0800" stop="20260226135500 +0800">
		<title lang="zh">喜羊羊与灰太狼之古古怪界有古怪</title>
	</programme>
	<programme channel="金鹰卡通" start="20260226135500 +0800" stop="20260226140000 +0800">
		<title lang="zh">麦咭播报堂</title>
	</programme>
	<programme channel="金鹰卡通" start="20260226140000 +0800" stop="20260226141300 +0800">
		<title lang="zh">奇妙萌可之闪耀流星(1)</title>
	</programme>
	<programme channel="金鹰卡通" start="20260226141300 +0800" stop="20260226142600 +0800">
		<title lang="zh">奇妙萌可之闪耀流星(2)</title>
	</programme>
	<programme channel="金鹰卡通" start="20260226142600 +0800" stop="20260226144000 +0800">
		<title lang="zh">奇妙萌可之闪耀流星(3)</title>
	</programme>
	<programme channel="金鹰卡通" start="20260226144000 +0800" stop="20260226145300 +0800">
		<title lang="zh">奇妙萌可之闪耀流星(4)</title>
	</programme>
	<programme channel="金鹰卡通" start="20260226145300 +0800" stop="20260226150600 +0800">
		<title lang="zh">奇妙萌可之闪耀流星(5)</title>
	</programme>
	<programme channel="金鹰卡通" start="20260226150600 +0800" stop="20260226152000 +0800">
		<title lang="zh">奇妙萌可之闪耀流星(6)</title>
	</programme>
	<programme channel="金鹰卡通" start="20260226152000 +0800" stop="20260226153300 +0800">
		<title lang="zh">奇妙萌可之闪耀流星(7)</title>
	</programme>
	<programme channel="金鹰卡通" start="20260226153300 +0800" stop="20260226154600 +0800">
		<title lang="zh">奇妙萌可之闪耀流星(8)</title>
	</programme>
	<programme channel="金鹰卡通" start="20260226154600 +0800" stop="20260226160000 +0800">
		<title lang="zh">奇妙萌可之闪耀流星(9)</title>
	</programme>
	<programme channel="金鹰卡通" start="20260226160000 +0800" stop="20260226160800 +0800">
		<title lang="zh">奶龙搞怪大作战2(4)</title>
	</programme>
	<programme channel="金鹰卡通" start="20260226160800 +0800" stop="20260226161700 +0800">
		<title lang="zh">奶龙搞怪大作战2(5)</title>
	</programme>
	<programme channel="金鹰卡通" start="20260226161700 +0800" stop="20260226162500 +0800">
		<title lang="zh">奶龙搞怪大作战2(6)</title>
	</programme>
	<programme channel="金鹰卡通" start="20260226162500 +0800" stop="20260226163400 +0800">
		<title lang="zh">奶龙搞怪大作战2(7)</title>
	</programme>
	<programme channel="金鹰卡通" start="20260226163400 +0800" stop="20260226164200 +0800">
		<title lang="zh">奶龙搞怪大作战2(8)</title>
	</programme>
	<programme channel="金鹰卡通" start="20260226164200 +0800" stop="20260226165100 +0800">
		<title lang="zh">奶龙搞怪大作战2(9)</title>
	</programme>
	<programme channel="金鹰卡通" start="20260226165100 +0800" stop="20260226170000 +0800">
		<title lang="zh">奶龙搞怪大作战2(10)</title>
	</programme>
	<programme channel="金鹰卡通" start="20260226170000 +0800" stop="20260226172000 +0800">
		<title lang="zh">麦咭帮帮队</title>
	</programme>
	<programme channel="金鹰卡通" start="20260226172000 +0800" stop="20260226172400 +0800">
		<title lang="zh">奶龙搞怪大作战1(1)</title>
	</programme>
	<programme channel="金鹰卡通" start="20260226172400 +0800" stop="20260226172800 +0800">
		<title lang="zh">奶龙搞怪大作战1(2)</title>
	</programme>
	<programme channel="金鹰卡通" start="20260226172800 +0800" stop="20260226173200 +0800">
		<title lang="zh">奶龙搞怪大作战1(3)</title>
	</programme>
	<programme channel="金鹰卡通" start="20260226173200 +0800" stop="20260226173600 +0800">
		<title lang="zh">奶龙搞怪大作战1(4)</title>
	</programme>
	<programme channel="金鹰卡通" start="20260226173600 +0800" stop="20260226174000 +0800">
		<title lang="zh">奶龙搞怪大作战1(5)</title>
	</programme>
	<programme channel="金鹰卡通" start="20260226174000 +0800" stop="20260226174400 +0800">
		<title lang="zh">奶龙搞怪大作战1(6)</title>
	</programme>
	<programme channel="金鹰卡通" start="20260226174400 +0800" stop="20260226174800 +0800">
		<title lang="zh">奶龙搞怪大作战1(7)</title>
	</programme>
	<programme channel="金鹰卡通" start="20260226174800 +0800" stop="20260226175200 +0800">
		<title lang="zh">奶龙搞怪大作战1(8)</title>
	</programme>
	<programme channel="金鹰卡通" start="20260226175200 +0800" stop="20260226175600 +0800">
		<title lang="zh">奶龙搞怪大作战1(9)</title>
	</programme>
	<programme channel="金鹰卡通" start="20260226175600 +0800" stop="20260226180000 +0800">
		<title lang="zh">奶龙搞怪大作战1(10)</title>
	</programme>
	<programme channel="金鹰卡通" start="20260226180000 +0800" stop="20260226181200 +0800">
		<title lang="zh">熊出没之探险日记2(6)</title>
	</programme>
	<programme channel="金鹰卡通" start="20260226181200 +0800" stop="20260226182400 +0800">
		<title lang="zh">熊出没之探险日记2(7)</title>
	</programme>
	<programme channel="金鹰卡通" start="20260226182400 +0800" stop="20260226183600 +0800">
		<title lang="zh">熊出没之探险日记2(8)</title>
	</programme>
	<programme channel="金鹰卡通" start="20260226183600 +0800" stop="20260226184800 +0800">
		<title lang="zh">熊出没之探险日记2(9)</title>
	</programme>
	<programme channel="金鹰卡通" start="20260226184800 +0800" stop="20260226190000 +0800">
		<title lang="zh">熊出没之探险日记2(10)</title>
	</programme>
	<programme channel="金鹰卡通" start="20260226190000 +0800" stop="20260226190300 +0800">
		<title lang="zh">新声时刻</title>
	</programme>
	<programme channel="金鹰卡通" start="20260226190300 +0800" stop="20260226191200 +0800">
		<title lang="zh">喜羊羊与灰太狼之奇侠大营救(33)</title>
	</programme>
	<programme channel="金鹰卡通" start="20260226191200 +0800" stop="20260226192200 +0800">
		<title lang="zh">喜羊羊与灰太狼之奇侠大营救(34)</title>
	</programme>
	<programme channel="金鹰卡通" start="20260226192200 +0800" stop="20260226193200 +0800">
		<title lang="zh">喜羊羊与灰太狼之奇侠大营救(35)</title>
	</programme>
	<programme channel="金鹰卡通" start="20260226193200 +0800" stop="20260226194200 +0800">
		<title lang="zh">喜羊羊与灰太狼之奇侠大营救(36)</title>
	</programme>
	<programme channel="金鹰卡通" start="20260226194200 +0800" stop="20260226195200 +0800">
		<title lang="zh">喜羊羊与灰太狼之奇侠大营救(37)</title>
	</programme>
	<programme channel="金鹰卡通" start="20260226195200 +0800" stop="20260226200200 +0800">
		<title lang="zh">喜羊羊与灰太狼之奇侠大营救(38)</title>
	</programme>
	<programme channel="金鹰卡通" start="20260226200200 +0800" stop="20260226201100 +0800">
		<title lang="zh">喜羊羊与灰太狼之奇侠大营救(39)</title>
	</programme>
	<programme channel="金鹰卡通" start="20260226201100 +0800" stop="20260226202100 +0800">
		<title lang="zh">喜羊羊与灰太狼之奇侠大营救(40)</title>
	</programme>
	<programme channel="金鹰卡通" start="20260226202100 +0800" stop="20260226203100 +0800">
		<title lang="zh">喜羊羊与灰太狼之奇侠大营救(41)</title>
	</programme>
	<programme channel="金鹰卡通" start="20260226203100 +0800" stop="20260226204100 +0800">
		<title lang="zh">喜羊羊与灰太狼之奇侠大营救(42)</title>
	</programme>
	<programme channel="金鹰卡通" start="20260226204100 +0800" stop="20260226205100 +0800">
		<title lang="zh">喜羊羊与灰太狼之奇侠大营救(43)</title>
	</programme>
	<programme channel="金鹰卡通" start="20260226205100 +0800" stop="20260226210100 +0800">
		<title lang="zh">喜羊羊与灰太狼之奇侠大营救(44)</title>
	</programme>
	<programme channel="金鹰卡通" start="20260226210100 +0800" stop="20260226211000 +0800">
		<title lang="zh">喜羊羊与灰太狼之奇侠大营救(45)</title>
	</programme>
	<programme channel="金鹰卡通" start="20260226211000 +0800" stop="20260226212000 +0800">
		<title lang="zh">喜羊羊与灰太狼之奇侠大营救(46)</title>
	</programme>
	<programme channel="金鹰卡通" start="20260226212000 +0800" stop="20260226213000 +0800">
		<title lang="zh">喜羊羊与灰太狼之奇侠大营救(47)</title>
	</programme>
	<programme channel="金鹰卡通" start="20260226213000 +0800" stop="20260226214000 +0800">
		<title lang="zh">喜羊羊与灰太狼之奇侠大营救(48)</title>
	</programme>
	<programme channel="金鹰卡通" start="20260226214000 +0800" stop="20260226215000 +0800">
		<title lang="zh">喜羊羊与灰太狼之奇侠大营救(49)</title>
	</programme>
	<programme channel="金鹰卡通" start="20260226215000 +0800" stop="20260226220000 +0800">
		<title lang="zh">喜羊羊与灰太狼之奇侠大营救(50)</title>
	</programme>
	<programme channel="金鹰卡通" start="20260226220000 +0800" stop="20260226231000 +0800">
		<title lang="zh">中国新声代2026(3)</title>
	</programme>
	<programme channel="金鹰卡通" start="20260226231000 +0800" stop="20260226232000 +0800">
		<title lang="zh">熊出没之探险日记1(22)</title>
	</programme>
	<programme channel="金鹰卡通" start="20260226232000 +0800" stop="20260226233000 +0800">
		<title lang="zh">熊出没之探险日记1(23)</title>
	</programme>
	<programme channel="金鹰卡通" start="20260226233000 +0800" stop="20260226234000 +0800">
		<title lang="zh">熊出没之探险日记1(24)</title>
	</programme>
	<programme channel="金鹰卡通" start="20260226234000 +0800" stop="20260226235000 +0800">
		<title lang="zh">熊出没之探险日记1(25)</title>
	</programme>
	<programme channel="金鹰卡通" start="20260226235000 +0800" stop="20260226235900 +0800">
		<title lang="zh">熊出没之探险日记1(26)</title>
	</programme>
	<programme channel="金鹰卡通" start="20260226235900 +0800" stop="20260227000000 +0800">
		<title lang="zh">结束</title>
	</programme>
	<channel id="凤凰中文">
		<display-name lang="zh">凤凰中文</display-name>
	</channel>
	<programme channel="凤凰中文" start="20260225000000 +0800" stop="20260225005700 +0800">
		<title lang="zh">凤凰洲际快车 -25/2/26</title>
	</programme>
	<programme channel="凤凰中文" start="20260225005700 +0800" stop="20260225010000 +0800">
		<title lang="zh">凤凰气象站</title>
	</programme>
	<programme channel="凤凰中文" start="20260225010000 +0800" stop="20260225013000 +0800">
		<title lang="zh">有报天天读 -24/2/26</title>
	</programme>
	<programme channel="凤凰中文" start="20260225013000 +0800" stop="20260225020000 +0800">
		<title lang="zh">凤凰大视野</title>
	</programme>
	<programme channel="凤凰中文" start="20260225020000 +0800" stop="20260225023000 +0800">
		<title lang="zh">纪录大时代 第1424集</title>
	</programme>
	<programme channel="凤凰中文" start="20260225023000 +0800" stop="20260225030000 +0800">
		<title lang="zh">亚洲财经透视 第1080集</title>
	</programme>
	<programme channel="凤凰中文" start="20260225030000 +0800" stop="20260225033000 +0800">
		<title lang="zh">新闻今日谈 -24/2/26</title>
	</programme>
	<programme channel="凤凰中文" start="20260225033000 +0800" stop="20260225040000 +0800">
		<title lang="zh">凤凰聚焦 第1082集</title>
	</programme>
	<programme channel="凤凰中文" start="20260225040000 +0800" stop="20260225043000 +0800">
		<title lang="zh">我们和牠们 第158集</title>
	</programme>
	<programme channel="凤凰中文" start="20260225043000 +0800" stop="20260225050000 +0800">
		<title lang="zh">凤凰全球连线 -24/2/26</title>
	</programme>
	<programme channel="凤凰中文" start="20260225050000 +0800" stop="20260225053000 +0800">
		<title lang="zh">有报天天读 -24/2/26</title>
	</programme>
	<programme channel="凤凰中文" start="20260225053000 +0800" stop="20260225060000 +0800">
		<title lang="zh">凤凰冲击播 第680集 -时事亮亮点</title>
	</programme>
	<programme channel="凤凰中文" start="20260225060000 +0800" stop="20260225063000 +0800">
		<title lang="zh">纪录大时代 第1424集</title>
	</programme>
	<programme channel="凤凰中文" start="20260225063000 +0800" stop="20260225070000 +0800">
		<title lang="zh">总编辑时间 -24/2/26</title>
	</programme>
	<programme channel="凤凰中文" start="20260225070000 +0800" stop="20260225075700 +0800">
		<title lang="zh">凤凰早班车 -25/2/26</title>
	</programme>
	<programme channel="凤凰中文" start="20260225075700 +0800" stop="20260225080000 +0800">
		<title lang="zh">凤凰气象站</title>
	</programme>
	<programme channel="凤凰中文" start="20260225080000 +0800" stop="20260225085700 +0800">
		<title lang="zh">凤凰早班车 -25/2/26</title>
	</programme>
	<programme channel="凤凰中文" start="20260225085700 +0800" stop="20260225090000 +0800">
		<title lang="zh">凤凰气象站</title>
	</programme>
	<programme channel="凤凰中文" start="20260225090000 +0800" stop="20260225093000 +0800">
		<title lang="zh">凤凰全球连线 -24/2/26</title>
	</programme>
	<programme channel="凤凰中文" start="20260225093000 +0800" stop="20260225100000 +0800">
		<title lang="zh">凤凰大视野</title>
	</programme>
	<programme channel="凤凰中文" start="20260225100000 +0800" stop="20260225105700 +0800">
		<title lang="zh">凤凰正点播报 1000 -25/2/26</title>
	</programme>
	<programme channel="凤凰中文" start="20260225105700 +0800" stop="20260225110000 +0800">
		<title lang="zh">凤凰气象站</title>
	</programme>
	<programme channel="凤凰中文" start="20260225110000 +0800" stop="20260225113000 +0800">
		<title lang="zh">凤凰聚焦 第1082集</title>
	</programme>
	<programme channel="凤凰中文" start="20260225113000 +0800" stop="20260225120000 +0800">
		<title lang="zh">有报天天读 -25/2/26</title>
	</programme>
	<programme channel="凤凰中文" start="20260225120000 +0800" stop="20260225125500 +0800">
		<title lang="zh">凤凰午间专列 -25/2/26</title>
	</programme>
	<programme channel="凤凰中文" start="20260225125500 +0800" stop="20260225130000 +0800">
		<title lang="zh">凤凰气象站</title>
	</programme>
	<programme channel="凤凰中文" start="20260225130000 +0800" stop="20260225133000 +0800">
		<title lang="zh">总编辑时间 -24/2/26</title>
	</programme>
	<programme channel="凤凰中文" start="20260225133000 +0800" stop="20260225140000 +0800">
		<title lang="zh">近观中国 第213集</title>
	</programme>
	<programme channel="凤凰中文" start="20260225140000 +0800" stop="20260225143000 +0800">
		<title lang="zh">石评天下 第145集</title>
	</programme>
	<programme channel="凤凰中文" start="20260225143000 +0800" stop="20260225150000 +0800">
		<title lang="zh">凤凰大视野</title>
	</programme>
	<programme channel="凤凰中文" start="20260225150000 +0800" stop="20260225155700 +0800">
		<title lang="zh">凤凰正点播报 1500 -25/2/26</title>
	</programme>
	<programme channel="凤凰中文" start="20260225155700 +0800" stop="20260225160000 +0800">
		<title lang="zh">凤凰气象站</title>
	</programme>
	<programme channel="凤凰中文" start="20260225160000 +0800" stop="20260225163000 +0800">
		<title lang="zh">凤凰冲击播 第680集 -时事亮亮点</title>
	</programme>
	<programme channel="凤凰中文" start="20260225163000 +0800" stop="20260225170000 +0800">
		<title lang="zh">纪录大时代 第1425集</title>
	</programme>
	<programme channel="凤凰中文" start="20260225170000 +0800" stop="20260225173000 +0800">
		<title lang="zh">我们和牠们 第158集</title>
	</programme>
	<programme channel="凤凰中文" start="20260225173000 +0800" stop="20260225180000 +0800">
		<title lang="zh">有报天天读 -25/2/26</title>
	</programme>
	<programme channel="凤凰中文" start="20260225180000 +0800" stop="20260225182700 +0800">
		<title lang="zh">凤凰焦点新闻 1800 -25/2/26</title>
	</programme>
	<programme channel="凤凰中文" start="20260225182700 +0800" stop="20260225183000 +0800">
		<title lang="zh">凤凰气象站</title>
	</programme>
	<programme channel="凤凰中文" start="20260225183000 +0800" stop="20260225190000 +0800">
		<title lang="zh">新闻今日谈 -25/2/26</title>
	</programme>
	<programme channel="凤凰中文" start="20260225190000 +0800" stop="20260225193000 +0800">
		<title lang="zh">亚洲财经透视 第1081集</title>
	</programme>
	<programme channel="凤凰中文" start="20260225193000 +0800" stop="20260225200000 +0800">
		<title lang="zh">总编辑时间 -25/2/26</title>
	</programme>
	<programme channel="凤凰中文" start="20260225200000 +0800" stop="20260225203000 +0800">
		<title lang="zh">凤凰大视野</title>
	</programme>
	<programme channel="凤凰中文" start="20260225203000 +0800" stop="20260225210000 +0800">
		<title lang="zh">凤凰冲击播 第377集 -军情观察室</title>
	</programme>
	<programme channel="凤凰中文" start="20260225210000 +0800" stop="20260225215500 +0800">
		<title lang="zh">时事直通车 -25/2/26</title>
	</programme>
	<programme channel="凤凰中文" start="20260225215500 +0800" stop="20260225220000 +0800">
		<title lang="zh">凤凰气象站</title>
	</programme>
	<programme channel="凤凰中文" start="20260225220000 +0800" stop="20260225223000 +0800">
		<title lang="zh">凤凰聚焦 第1083集</title>
	</programme>
	<programme channel="凤凰中文" start="20260225223000 +0800" stop="20260225230000 +0800">
		<title lang="zh">凤凰全球连线 -25/2/26</title>
	</programme>
	<programme channel="凤凰中文" start="20260225230000 +0800" stop="20260225233000 +0800">
		<title lang="zh">亚洲财经透视 第1081集</title>
	</programme>
	<programme channel="凤凰中文" start="20260225233000 +0800" stop="20260226000000 +0800">
		<title lang="zh">新闻今日谈 -25/2/26</title>
	</programme>
	<programme channel="凤凰中文" start="20260226000000 +0800" stop="20260226005700 +0800">
		<title lang="zh">凤凰洲际快车 -26/2/26</title>
	</programme>
	<programme channel="凤凰中文" start="20260226005700 +0800" stop="20260226010000 +0800">
		<title lang="zh">凤凰气象站</title>
	</programme>
	<programme channel="凤凰中文" start="20260226010000 +0800" stop="20260226013000 +0800">
		<title lang="zh">有报天天读 -25/2/26</title>
	</programme>
	<programme channel="凤凰中文" start="20260226013000 +0800" stop="20260226020000 +0800">
		<title lang="zh">凤凰大视野</title>
	</programme>
	<programme channel="凤凰中文" start="20260226020000 +0800" stop="20260226023000 +0800">
		<title lang="zh">纪录大时代 第1425集</title>
	</programme>
	<programme channel="凤凰中文" start="20260226023000 +0800" stop="20260226030000 +0800">
		<title lang="zh">亚洲财经透视 第1081集</title>
	</programme>
	<programme channel="凤凰中文" start="20260226030000 +0800" stop="20260226033000 +0800">
		<title lang="zh">新闻今日谈 -25/2/26</title>
	</programme>
	<programme channel="凤凰中文" start="20260226033000 +0800" stop="20260226040000 +0800">
		<title lang="zh">凤凰聚焦 第1083集</title>
	</programme>
	<programme channel="凤凰中文" start="20260226040000 +0800" stop="20260226043000 +0800">
		<title lang="zh">石评天下 第145集</title>
	</programme>
	<programme channel="凤凰中文" start="20260226043000 +0800" stop="20260226050000 +0800">
		<title lang="zh">凤凰全球连线 -25/2/26</title>
	</programme>
	<programme channel="凤凰中文" start="20260226050000 +0800" stop="20260226053000 +0800">
		<title lang="zh">有报天天读 -25/2/26</title>
	</programme>
	<programme channel="凤凰中文" start="20260226053000 +0800" stop="20260226060000 +0800">
		<title lang="zh">凤凰冲击播 第377集 -军情观察室</title>
	</programme>
	<programme channel="凤凰中文" start="20260226060000 +0800" stop="20260226063000 +0800">
		<title lang="zh">纪录大时代 第1425集</title>
	</programme>
	<programme channel="凤凰中文" start="20260226063000 +0800" stop="20260226070000 +0800">
		<title lang="zh">总编辑时间 -25/2/26</title>
	</programme>
	<programme channel="凤凰中文" start="20260226070000 +0800" stop="20260226075700 +0800">
		<title lang="zh">凤凰早班车 -26/2/26</title>
	</programme>
	<programme channel="凤凰中文" start="20260226075700 +0800" stop="20260226080000 +0800">
		<title lang="zh">凤凰气象站</title>
	</programme>
	<programme channel="凤凰中文" start="20260226080000 +0800" stop="20260226085700 +0800">
		<title lang="zh">凤凰早班车 -26/2/26</title>
	</programme>
	<programme channel="凤凰中文" start="20260226085700 +0800" stop="20260226090000 +0800">
		<title lang="zh">凤凰气象站</title>
	</programme>
	<programme channel="凤凰中文" start="20260226090000 +0800" stop="20260226093000 +0800">
		<title lang="zh">凤凰全球连线 -25/2/26</title>
	</programme>
	<programme channel="凤凰中文" start="20260226093000 +0800" stop="20260226100000 +0800">
		<title lang="zh">凤凰大视野</title>
	</programme>
	<programme channel="凤凰中文" start="20260226100000 +0800" stop="20260226105700 +0800">
		<title lang="zh">凤凰正点播报 1000 -26/2/26</title>
	</programme>
	<programme channel="凤凰中文" start="20260226105700 +0800" stop="20260226110000 +0800">
		<title lang="zh">凤凰气象站</title>
	</programme>
	<programme channel="凤凰中文" start="20260226110000 +0800" stop="20260226113000 +0800">
		<title lang="zh">凤凰聚焦 第1083集</title>
	</programme>
	<programme channel="凤凰中文" start="20260226113000 +0800" stop="20260226120000 +0800">
		<title lang="zh">有报天天读 -26/2/26</title>
	</programme>
	<programme channel="凤凰中文" start="20260226120000 +0800" stop="20260226125500 +0800">
		<title lang="zh">凤凰午间专列 -26/2/26</title>
	</programme>
	<programme channel="凤凰中文" start="20260226125500 +0800" stop="20260226130000 +0800">
		<title lang="zh">凤凰气象站</title>
	</programme>
	<programme channel="凤凰中文" start="20260226130000 +0800" stop="20260226133000 +0800">
		<title lang="zh">总编辑时间 -25/2/26</title>
	</programme>
	<programme channel="凤凰中文" start="20260226133000 +0800" stop="20260226140000 +0800">
		<title lang="zh">发现大湾区 第159集</title>
	</programme>
	<programme channel="凤凰中文" start="20260226140000 +0800" stop="20260226143000 +0800">
		<title lang="zh">文化大观园 第462集</title>
	</programme>
	<programme channel="凤凰中文" start="20260226143000 +0800" stop="20260226150000 +0800">
		<title lang="zh">凤凰大视野</title>
	</programme>
	<programme channel="凤凰中文" start="20260226150000 +0800" stop="20260226155700 +0800">
		<title lang="zh">凤凰正点播报 1500 -26/2/26</title>
	</programme>
	<programme channel="凤凰中文" start="20260226155700 +0800" stop="20260226160000 +0800">
		<title lang="zh">凤凰气象站</title>
	</programme>
	<programme channel="凤凰中文" start="20260226160000 +0800" stop="20260226163000 +0800">
		<title lang="zh">凤凰冲击播 第377集 -军情观察室</title>
	</programme>
	<programme channel="凤凰中文" start="20260226163000 +0800" stop="20260226170000 +0800">
		<title lang="zh">纪录大时代 第1426集</title>
	</programme>
	<programme channel="凤凰中文" start="20260226170000 +0800" stop="20260226171500 +0800">
		<title lang="zh">我的香港故事 第213集</title>
	</programme>
	<programme channel="凤凰中文" start="20260226171500 +0800" stop="20260226173000 +0800">
		<title lang="zh">我的香港故事 第212集</title>
	</programme>
	<programme channel="凤凰中文" start="20260226173000 +0800" stop="20260226180000 +0800">
		<title lang="zh">有报天天读 -26/2/26</title>
	</programme>
	<programme channel="凤凰中文" start="20260226180000 +0800" stop="20260226182700 +0800">
		<title lang="zh">凤凰焦点新闻 1800 -26/2/26</title>
	</programme>
	<programme channel="凤凰中文" start="20260226182700 +0800" stop="20260226183000 +0800">
		<title lang="zh">凤凰气象站</title>
	</programme>
	<programme channel="凤凰中文" start="20260226183000 +0800" stop="20260226190000 +0800">
		<title lang="zh">新闻今日谈 -26/2/26</title>
	</programme>
	<programme channel="凤凰中文" start="20260226190000 +0800" stop="20260226193000 +0800">
		<title lang="zh">亚洲财经透视 第1082集</title>
	</programme>
	<programme channel="凤凰中文" start="20260226193000 +0800" stop="20260226200000 +0800">
		<title lang="zh">总编辑时间 -26/2/26</title>
	</programme>
	<programme channel="凤凰中文" start="20260226200000 +0800" stop="20260226203000 +0800">
		<title lang="zh">凤凰大视野</title>
	</programme>
	<programme channel="凤凰中文" start="20260226203000 +0800" stop="20260226210000 +0800">
		<title lang="zh">凤凰冲击播 第409集 -风云对话</title>
	</programme>
	<programme channel="凤凰中文" start="20260226210000 +0800" stop="20260226215500 +0800">
		<title lang="zh">时事直通车 -26/2/26</title>
	</programme>
	<programme channel="凤凰中文" start="20260226215500 +0800" stop="20260226220000 +0800">
		<title lang="zh">凤凰气象站</title>
	</programme>
	<programme channel="凤凰中文" start="20260226220000 +0800" stop="20260226223000 +0800">
		<title lang="zh">凤凰聚焦 第1084集</title>
	</programme>
	<programme channel="凤凰中文" start="20260226223000 +0800" stop="20260226230000 +0800">
		<title lang="zh">凤凰全球连线 -26/2/26</title>
	</programme>
	<programme channel="凤凰中文" start="20260226230000 +0800" stop="20260226233000 +0800">
		<title lang="zh">亚洲财经透视 第1082集</title>
	</programme>
	<programme channel="凤凰中文" start="20260226233000 +0800" stop="20260227000000 +0800">
		<title lang="zh">新闻今日谈 -26/2/26</title>
	</programme>
	<channel id="凤凰资讯">
		<display-name lang="zh">凤凰资讯</display-name>
	</channel>
	<programme channel="凤凰资讯" start="20260225060000 +0800" stop="20260225062700 +0800">
		<title lang="zh">凤凰正点播报 0100 (25/2/26)(RP)</title>
	</programme>
	<programme channel="凤凰资讯" start="20260225062700 +0800" stop="20260225063000 +0800">
		<title lang="zh">凤凰气象站</title>
	</programme>
	<programme channel="凤凰资讯" start="20260225063000 +0800" stop="20260225070000 +0800">
		<title lang="zh">凤凰聚焦 (1082)</title>
	</programme>
	<programme channel="凤凰资讯" start="20260225070000 +0800" stop="20260225075700 +0800">
		<title lang="zh">凤凰早班车 (25/2/26)</title>
	</programme>
	<programme channel="凤凰资讯" start="20260225075700 +0800" stop="20260225080000 +0800">
		<title lang="zh">凤凰气象站</title>
	</programme>
	<programme channel="凤凰资讯" start="20260225080000 +0800" stop="20260225085700 +0800">
		<title lang="zh">(续)凤凰早班车 (25/2/26)</title>
	</programme>
	<programme channel="凤凰资讯" start="20260225085700 +0800" stop="20260225090000 +0800">
		<title lang="zh">凤凰气象站</title>
	</programme>
	<programme channel="凤凰资讯" start="20260225090000 +0800" stop="20260225092700 +0800">
		<title lang="zh">凤凰正点播报 0900 (25/2/26)</title>
	</programme>
	<programme channel="凤凰资讯" start="20260225092700 +0800" stop="20260225093000 +0800">
		<title lang="zh">凤凰气象站</title>
	</programme>
	<programme channel="凤凰资讯" start="20260225093000 +0800" stop="20260225100000 +0800">
		<title lang="zh">金石财经
 (24/2/26)(RP)</title>
	</programme>
	<programme channel="凤凰资讯" start="20260225100000 +0800" stop="20260225105700 +0800">
		<title lang="zh">凤凰正点播报 1000 (25/2/26)</title>
	</programme>
	<programme channel="凤凰资讯" start="20260225105700 +0800" stop="20260225110000 +0800">
		<title lang="zh">凤凰气象站</title>
	</programme>
	<programme channel="凤凰资讯" start="20260225110000 +0800" stop="20260225112700 +0800">
		<title lang="zh">凤凰正点播报 1100 (25/2/26)</title>
	</programme>
	<programme channel="凤凰资讯" start="20260225112700 +0800" stop="20260225113000 +0800">
		<title lang="zh">凤凰气象站</title>
	</programme>
	<programme channel="凤凰资讯" start="20260225113000 +0800" stop="20260225120000 +0800">
		<title lang="zh">总编辑时间 
(24/2/26)(RP)</title>
	</programme>
	<programme channel="凤凰资讯" start="20260225120000 +0800" stop="20260225125500 +0800">
		<title lang="zh">*深圳锦绣中华民俗村 凤凰午间专列
 (25/2/26)</title>
	</programme>
	<programme channel="凤凰资讯" start="20260225125500 +0800" stop="20260225130000 +0800">
		<title lang="zh">凤凰气象站</title>
	</programme>
	<programme channel="凤凰资讯" start="20260225130000 +0800" stop="20260225132700 +0800">
		<title lang="zh">凤凰正点播报 1300 (25/2/26)</title>
	</programme>
	<programme channel="凤凰资讯" start="20260225132700 +0800" stop="20260225133000 +0800">
		<title lang="zh">凤凰气象站</title>
	</programme>
	<programme channel="凤凰资讯" start="20260225133000 +0800" stop="20260225140000 +0800">
		<title lang="zh">金石财经
 (24/2/26)(RP)</title>
	</programme>
	<programme channel="凤凰资讯" start="20260225140000 +0800" stop="20260225142700 +0800">
		<title lang="zh">凤凰正点播报 1400 (25/2/26)</title>
	</programme>
	<programme channel="凤凰资讯" start="20260225142700 +0800" stop="20260225143000 +0800">
		<title lang="zh">凤凰气象站</title>
	</programme>
	<programme channel="凤凰资讯" start="20260225143000 +0800" stop="20260225150000 +0800">
		<title lang="zh">总编辑时间 (24/2/26)(RP)</title>
	</programme>
	<programme channel="凤凰资讯" start="20260225150000 +0800" stop="20260225155700 +0800">
		<title lang="zh">凤凰正点播报 1500  (25/2/26)</title>
	</programme>
	<programme channel="凤凰资讯" start="20260225155700 +0800" stop="20260225160000 +0800">
		<title lang="zh">凤凰气象站</title>
	</programme>
	<programme channel="凤凰资讯" start="20260225160000 +0800" stop="20260225165700 +0800">
		<title lang="zh">凤凰正点播报 1600  (25/2/26)</title>
	</programme>
	<programme channel="凤凰资讯" start="20260225165700 +0800" stop="20260225170000 +0800">
		<title lang="zh">凤凰气象站</title>
	</programme>
	<programme channel="凤凰资讯" start="20260225170000 +0800" stop="20260225172700 +0800">
		<title lang="zh">凤凰正点播报 1700 (25/2/26)</title>
	</programme>
	<programme channel="凤凰资讯" start="20260225172700 +0800" stop="20260225173000 +0800">
		<title lang="zh">凤凰气象站</title>
	</programme>
	<programme channel="凤凰资讯" start="20260225173000 +0800" stop="20260225180000 +0800">
		<title lang="zh">金石财经 (25/2/26)</title>
	</programme>
	<programme channel="凤凰资讯" start="20260225180000 +0800" stop="20260225182700 +0800">
		<title lang="zh">*阳光保险 
凤凰焦点新闻 1800 (25/2/26)</title>
	</programme>
	<programme channel="凤凰资讯" start="20260225182700 +0800" stop="20260225183000 +0800">
		<title lang="zh">凤凰气象站</title>
	</programme>
	<programme channel="凤凰资讯" start="20260225183000 +0800" stop="20260225190000 +0800">
		<title lang="zh">*以岭药业 新闻今日谈 (25/2/26)</title>
	</programme>
	<programme channel="凤凰资讯" start="20260225190000 +0800" stop="20260225195700 +0800">
		<title lang="zh">*赛轮轮胎 华闻大直播  (25/2/26)</title>
	</programme>
	<programme channel="凤凰资讯" start="20260225195700 +0800" stop="20260225200000 +0800">
		<title lang="zh">凤凰气象站</title>
	</programme>
	<programme channel="凤凰资讯" start="20260225200000 +0800" stop="20260225202700 +0800">
		<title lang="zh">*阳光保险 
凤凰焦点新闻 2000
 (25/2/26)</title>
	</programme>
	<programme channel="凤凰资讯" start="20260225202700 +0800" stop="20260225203000 +0800">
		<title lang="zh">凤凰气象站</title>
	</programme>
	<programme channel="凤凰资讯" start="20260225203000 +0800" stop="20260225210000 +0800">
		<title lang="zh">*临工 凤凰财经日报 (25/2/26)</title>
	</programme>
	<programme channel="凤凰资讯" start="20260225210000 +0800" stop="20260225215500 +0800">
		<title lang="zh">*五粮液 时事直通车  (25/2/26)</title>
	</programme>
	<programme channel="凤凰资讯" start="20260225215500 +0800" stop="20260225220000 +0800">
		<title lang="zh">凤凰气象站</title>
	</programme>
	<programme channel="凤凰资讯" start="20260225220000 +0800" stop="20260225223000 +0800">
		<title lang="zh">总编辑时间 (25/2/26)</title>
	</programme>
	<programme channel="凤凰资讯" start="20260225223000 +0800" stop="20260225230000 +0800">
		<title lang="zh">*以岭药业 新闻今日谈 (25/2/26)(RP)</title>
	</programme>
	<programme channel="凤凰资讯" start="20260225230000 +0800" stop="20260225232700 +0800">
		<title lang="zh">*阳光保险 
凤凰焦点新闻 2300
(25/2/26)</title>
	</programme>
	<programme channel="凤凰资讯" start="20260225232700 +0800" stop="20260225233000 +0800">
		<title lang="zh">凤凰气象站</title>
	</programme>
	<programme channel="凤凰资讯" start="20260225233000 +0800" stop="20260225235959 +0800">
		<title lang="zh">总编辑时间 (25/2/26)(RP)</title>
	</programme>
	<programme channel="凤凰资讯" start="20260226060000 +0800" stop="20260226062700 +0800">
		<title lang="zh">凤凰正点播报 0100 (26/2/26)(RP)</title>
	</programme>
	<programme channel="凤凰资讯" start="20260226062700 +0800" stop="20260226063000 +0800">
		<title lang="zh">凤凰气象站</title>
	</programme>
	<programme channel="凤凰资讯" start="20260226063000 +0800" stop="20260226070000 +0800">
		<title lang="zh">凤凰聚焦 (1083)</title>
	</programme>
	<programme channel="凤凰资讯" start="20260226070000 +0800" stop="20260226075700 +0800">
		<title lang="zh">凤凰早班车 (26/2/26)</title>
	</programme>
	<programme channel="凤凰资讯" start="20260226075700 +0800" stop="20260226080000 +0800">
		<title lang="zh">凤凰气象站</title>
	</programme>
	<programme channel="凤凰资讯" start="20260226080000 +0800" stop="20260226085700 +0800">
		<title lang="zh">(续)凤凰早班车 (26/2/26)</title>
	</programme>
	<programme channel="凤凰资讯" start="20260226085700 +0800" stop="20260226090000 +0800">
		<title lang="zh">凤凰气象站</title>
	</programme>
	<programme channel="凤凰资讯" start="20260226090000 +0800" stop="20260226092700 +0800">
		<title lang="zh">凤凰正点播报 0900 (26/2/26)</title>
	</programme>
	<programme channel="凤凰资讯" start="20260226092700 +0800" stop="20260226093000 +0800">
		<title lang="zh">凤凰气象站</title>
	</programme>
	<programme channel="凤凰资讯" start="20260226093000 +0800" stop="20260226100000 +0800">
		<title lang="zh">金石财经
 (25/2/26)(RP)</title>
	</programme>
	<programme channel="凤凰资讯" start="20260226100000 +0800" stop="20260226105700 +0800">
		<title lang="zh">凤凰正点播报 1000 (26/2/26)</title>
	</programme>
	<programme channel="凤凰资讯" start="20260226105700 +0800" stop="20260226110000 +0800">
		<title lang="zh">凤凰气象站</title>
	</programme>
	<programme channel="凤凰资讯" start="20260226110000 +0800" stop="20260226112700 +0800">
		<title lang="zh">凤凰正点播报 1100 (26/2/26)</title>
	</programme>
	<programme channel="凤凰资讯" start="20260226112700 +0800" stop="20260226113000 +0800">
		<title lang="zh">凤凰气象站</title>
	</programme>
	<programme channel="凤凰资讯" start="20260226113000 +0800" stop="20260226120000 +0800">
		<title lang="zh">总编辑时间
 (25/2/26)(RP)</title>
	</programme>
	<programme channel="凤凰资讯" start="20260226120000 +0800" stop="20260226125500 +0800">
		<title lang="zh">*深圳锦绣中华民俗村 凤凰午间专列
 (26/2/26)</title>
	</programme>
	<programme channel="凤凰资讯" start="20260226125500 +0800" stop="20260226130000 +0800">
		<title lang="zh">凤凰气象站</title>
	</programme>
	<programme channel="凤凰资讯" start="20260226130000 +0800" stop="20260226132700 +0800">
		<title lang="zh">凤凰正点播报 1300 (26/2/26)</title>
	</programme>
	<programme channel="凤凰资讯" start="20260226132700 +0800" stop="20260226133000 +0800">
		<title lang="zh">凤凰气象站</title>
	</programme>
	<programme channel="凤凰资讯" start="20260226133000 +0800" stop="20260226140000 +0800">
		<title lang="zh">金石财经
 (25/2/26)(RP)</title>
	</programme>
	<programme channel="凤凰资讯" start="20260226140000 +0800" stop="20260226142700 +0800">
		<title lang="zh">凤凰正点播报 1400 (26/2/26)</title>
	</programme>
	<programme channel="凤凰资讯" start="20260226142700 +0800" stop="20260226143000 +0800">
		<title lang="zh">凤凰气象站</title>
	</programme>
	<programme channel="凤凰资讯" start="20260226143000 +0800" stop="20260226150000 +0800">
		<title lang="zh">总编辑时间 (25/2/26)(RP)</title>
	</programme>
	<programme channel="凤凰资讯" start="20260226150000 +0800" stop="20260226155700 +0800">
		<title lang="zh">凤凰正点播报 1500  (26/2/26)</title>
	</programme>
	<programme channel="凤凰资讯" start="20260226155700 +0800" stop="20260226160000 +0800">
		<title lang="zh">凤凰气象站</title>
	</programme>
	<programme channel="凤凰资讯" start="20260226160000 +0800" stop="20260226165700 +0800">
		<title lang="zh">凤凰正点播报 1600  (26/2/26)</title>
	</programme>
	<programme channel="凤凰资讯" start="20260226165700 +0800" stop="20260226170000 +0800">
		<title lang="zh">凤凰气象站</title>
	</programme>
	<programme channel="凤凰资讯" start="20260226170000 +0800" stop="20260226172700 +0800">
		<title lang="zh">凤凰正点播报 1700 (26/2/26)</title>
	</programme>
	<programme channel="凤凰资讯" start="20260226172700 +0800" stop="20260226173000 +0800">
		<title lang="zh">凤凰气象站</title>
	</programme>
	<programme channel="凤凰资讯" start="20260226173000 +0800" stop="20260226180000 +0800">
		<title lang="zh">金石财经 (26/2/26)</title>
	</programme>
	<programme channel="凤凰资讯" start="20260226180000 +0800" stop="20260226182700 +0800">
		<title lang="zh">*阳光保险 
凤凰焦点新闻 1800 (26/2/26)</title>
	</programme>
	<programme channel="凤凰资讯" start="20260226182700 +0800" stop="20260226183000 +0800">
		<title lang="zh">凤凰气象站</title>
	</programme>
	<programme channel="凤凰资讯" start="20260226183000 +0800" stop="20260226190000 +0800">
		<title lang="zh">*以岭药业 新闻今日谈 (26/2/26)</title>
	</programme>
	<programme channel="凤凰资讯" start="20260226190000 +0800" stop="20260226195700 +0800">
		<title lang="zh">*赛轮轮胎 华闻大直播  (26/2/26)</title>
	</programme>
	<programme channel="凤凰资讯" start="20260226195700 +0800" stop="20260226200000 +0800">
		<title lang="zh">凤凰气象站</title>
	</programme>
	<programme channel="凤凰资讯" start="20260226200000 +0800" stop="20260226202700 +0800">
		<title lang="zh">*阳光保险
 凤凰焦点新闻 2000
 (26/2/26)</title>
	</programme>
	<programme channel="凤凰资讯" start="20260226202700 +0800" stop="20260226203000 +0800">
		<title lang="zh">凤凰气象站</title>
	</programme>
	<programme channel="凤凰资讯" start="20260226203000 +0800" stop="20260226210000 +0800">
		<title lang="zh">*临工 凤凰财经日报 (26/2/26)</title>
	</programme>
	<programme channel="凤凰资讯" start="20260226210000 +0800" stop="20260226215500 +0800">
		<title lang="zh">*五粮液 时事直通车  (26/2/26)</title>
	</programme>
	<programme channel="凤凰资讯" start="20260226215500 +0800" stop="20260226220000 +0800">
		<title lang="zh">凤凰气象站</title>
	</programme>
	<programme channel="凤凰资讯" start="20260226220000 +0800" stop="20260226223000 +0800">
		<title lang="zh">总编辑时间 (26/2/26)</title>
	</programme>
	<programme channel="凤凰资讯" start="20260226223000 +0800" stop="20260226230000 +0800">
		<title lang="zh">*以岭药业 新闻今日谈 (26/2/26)(RP)</title>
	</programme>
	<programme channel="凤凰资讯" start="20260226230000 +0800" stop="20260226232700 +0800">
		<title lang="zh">*阳光保险 
凤凰焦点新闻 2300 
(26/2/26)</title>
	</programme>
	<programme channel="凤凰资讯" start="20260226232700 +0800" stop="20260226233000 +0800">
		<title lang="zh">凤凰气象站</title>
	</programme>
	<programme channel="凤凰资讯" start="20260226233000 +0800" stop="20260226235959 +0800">
		<title lang="zh">总编辑时间 (26/2/26)(RP)</title>
	</programme>
	<channel id="凤凰香港">
		<display-name lang="zh">凤凰香港</display-name>
	</channel>
	<programme channel="凤凰香港" start="20260225060000 +0800" stop="20260225063000 +0800">
		<title lang="zh">我们和牠们(102)(R)</title>
	</programme>
	<programme channel="凤凰香港" start="20260225063000 +0800" stop="20260225070000 +0800">
		<title lang="zh">凤凰大视野</title>
	</programme>
	<programme channel="凤凰香港" start="20260225070000 +0800" stop="20260225075700 +0800">
		<title lang="zh">凤凰早班车(25/2/26)</title>
	</programme>
	<programme channel="凤凰香港" start="20260225075700 +0800" stop="20260225080000 +0800">
		<title lang="zh">凤凰气象站</title>
	</programme>
	<programme channel="凤凰香港" start="20260225080000 +0800" stop="20260225085700 +0800">
		<title lang="zh">(续) 凤凰早班车(25/2/26)</title>
	</programme>
	<programme channel="凤凰香港" start="20260225085700 +0800" stop="20260225090000 +0800">
		<title lang="zh">凤凰气象站</title>
	</programme>
	<programme channel="凤凰香港" start="20260225090000 +0800" stop="20260225093000 +0800">
		<title lang="zh">总编辑时间(24/2/26)</title>
	</programme>
	<programme channel="凤凰香港" start="20260225093000 +0800" stop="20260225100000 +0800">
		<title lang="zh">问答神州(990)</title>
	</programme>
	<programme channel="凤凰香港" start="20260225100000 +0800" stop="20260225103000 +0800">
		<title lang="zh">香港热厨房(77)</title>
	</programme>
	<programme channel="凤凰香港" start="20260225103000 +0800" stop="20260225110000 +0800">
		<title lang="zh">凤凰大视野</title>
	</programme>
	<programme channel="凤凰香港" start="20260225110000 +0800" stop="20260225113000 +0800">
		<title lang="zh">时事大破解(24/2/26)</title>
	</programme>
	<programme channel="凤凰香港" start="20260225113000 +0800" stop="20260225120000 +0800">
		<title lang="zh">华润 凤凰聚焦(1082)</title>
	</programme>
	<programme channel="凤凰香港" start="20260225120000 +0800" stop="20260225125500 +0800">
		<title lang="zh">凤凰午间专列(25/2/26)</title>
	</programme>
	<programme channel="凤凰香港" start="20260225125500 +0800" stop="20260225130000 +0800">
		<title lang="zh">凤凰气象站</title>
	</programme>
	<programme channel="凤凰香港" start="20260225130000 +0800" stop="20260225135300 +0800">
		<title lang="zh">午间快线(25/2/26)</title>
	</programme>
	<programme channel="凤凰香港" start="20260225135300 +0800" stop="20260225135600 +0800">
		<title lang="zh">凤凰气象站</title>
	</programme>
	<programme channel="凤凰香港" start="20260225135600 +0800" stop="20260225140000 +0800">
		<title lang="zh">立法新星再出发(31/40)</title>
	</programme>
	<programme channel="凤凰香港" start="20260225140000 +0800" stop="20260225143000 +0800">
		<title lang="zh">总编辑时间(24/2/26)</title>
	</programme>
	<programme channel="凤凰香港" start="20260225143000 +0800" stop="20260225150000 +0800">
		<title lang="zh">问答神州(990)</title>
	</programme>
	<programme channel="凤凰香港" start="20260225150000 +0800" stop="20260225153000 +0800">
		<title lang="zh">香港热厨房(77)</title>
	</programme>
	<programme channel="凤凰香港" start="20260225153000 +0800" stop="20260225160000 +0800">
		<title lang="zh">时事大破解(24/2/26)</title>
	</programme>
	<programme channel="凤凰香港" start="20260225160000 +0800" stop="20260225163000 +0800">
		<title lang="zh">凤凰大视野</title>
	</programme>
	<programme channel="凤凰香港" start="20260225163000 +0800" stop="20260225170000 +0800">
		<title lang="zh">香港新视点(455)(R)</title>
	</programme>
	<programme channel="凤凰香港" start="20260225170000 +0800" stop="20260225173000 +0800">
		<title lang="zh">华润 凤凰聚焦(1082)</title>
	</programme>
	<programme channel="凤凰香港" start="20260225173000 +0800" stop="20260225180000 +0800">
		<title lang="zh">文化大观园(461)</title>
	</programme>
	<programme channel="凤凰香港" start="20260225180000 +0800" stop="20260225182700 +0800">
		<title lang="zh">凤凰焦点新闻 1800(25/2/26)</title>
	</programme>
	<programme channel="凤凰香港" start="20260225182700 +0800" stop="20260225183000 +0800">
		<title lang="zh">凤凰气象站</title>
	</programme>
	<programme channel="凤凰香港" start="20260225183000 +0800" stop="20260225190000 +0800">
		<title lang="zh">以岭药业 新闻今日谈 (25/2/26)</title>
	</programme>
	<programme channel="凤凰香港" start="20260225190000 +0800" stop="20260225195700 +0800">
		<title lang="zh">全球新闻报道(25/2/26)</title>
	</programme>
	<programme channel="凤凰香港" start="20260225195700 +0800" stop="20260225200000 +0800">
		<title lang="zh">凤凰气象站</title>
	</programme>
	<programme channel="凤凰香港" start="20260225200000 +0800" stop="20260225202800 +0800">
		<title lang="zh">时事大破解(25/2/26)</title>
	</programme>
	<programme channel="凤凰香港" start="20260225202800 +0800" stop="20260225203000 +0800">
		<title lang="zh">中国银行(香港) 直达大湾区(25/2/26)</title>
	</programme>
	<programme channel="凤凰香港" start="20260225203000 +0800" stop="20260225210000 +0800">
		<title lang="zh">发现大湾区(159)</title>
	</programme>
	<programme channel="凤凰香港" start="20260225210000 +0800" stop="20260225215500 +0800">
		<title lang="zh">时事直通车(25/2/26)</title>
	</programme>
	<programme channel="凤凰香港" start="20260225215500 +0800" stop="20260225220000 +0800">
		<title lang="zh">凤凰气象站</title>
	</programme>
	<programme channel="凤凰香港" start="20260225220000 +0800" stop="20260225223000 +0800">
		<title lang="zh">晚间专线(25/2/26)</title>
	</programme>
	<programme channel="凤凰香港" start="20260225223000 +0800" stop="20260225230000 +0800">
		<title lang="zh">凤凰全球连线(25/2/26)</title>
	</programme>
	<programme channel="凤凰香港" start="20260225230000 +0800" stop="20260225233000 +0800">
		<title lang="zh">总编辑时间(25/2/26)</title>
	</programme>
	<programme channel="凤凰香港" start="20260225233000 +0800" stop="20260225235959 +0800">
		<title lang="zh">中国银行(香港)亚洲财经透视 (1081)</title>
	</programme>
	<programme channel="凤凰香港" start="20260226060000 +0800" stop="20260226063000 +0800">
		<title lang="zh">我们和牠们  [普]</title>
	</programme>
	<programme channel="凤凰香港" start="20260226063000 +0800" stop="20260226070000 +0800">
		<title lang="zh">凤凰大视野:暗面:战场谜案调查  [普]</title>
	</programme>
	<programme channel="凤凰香港" start="20260226070000 +0800" stop="20260226075700 +0800">
		<title lang="zh">凤凰早班车  [普]</title>
	</programme>
	<programme channel="凤凰香港" start="20260226075700 +0800" stop="20260226080000 +0800">
		<title lang="zh">凤凰气象站 [普]</title>
	</programme>
	<programme channel="凤凰香港" start="20260226080000 +0800" stop="20260226085700 +0800">
		<title lang="zh">凤凰早班车  [普]</title>
	</programme>
	<programme channel="凤凰香港" start="20260226085700 +0800" stop="20260226090000 +0800">
		<title lang="zh">凤凰气象站  [普]</title>
	</programme>
	<programme channel="凤凰香港" start="20260226090000 +0800" stop="20260226093000 +0800">
		<title lang="zh">总编辑时间  [普]</title>
	</programme>
	<programme channel="凤凰香港" start="20260226093000 +0800" stop="20260226100000 +0800">
		<title lang="zh">时事亮亮点  [普]</title>
	</programme>
	<programme channel="凤凰香港" start="20260226100000 +0800" stop="20260226103000 +0800">
		<title lang="zh">发现大湾区 [粤]</title>
	</programme>
	<programme channel="凤凰香港" start="20260226103000 +0800" stop="20260226110000 +0800">
		<title lang="zh">凤凰大视野:暗面:战场谜案调查  [普]</title>
	</programme>
	<programme channel="凤凰香港" start="20260226110000 +0800" stop="20260226113000 +0800">
		<title lang="zh">时事大破解  [粤]</title>
	</programme>
	<programme channel="凤凰香港" start="20260226113000 +0800" stop="20260226120000 +0800">
		<title lang="zh">华润 凤凰聚焦  [普]</title>
	</programme>
	<programme channel="凤凰香港" start="20260226120000 +0800" stop="20260226125500 +0800">
		<title lang="zh">凤凰午间专列  [普]</title>
	</programme>
	<programme channel="凤凰香港" start="20260226125500 +0800" stop="20260226130000 +0800">
		<title lang="zh">凤凰气象站 [普]</title>
	</programme>
	<programme channel="凤凰香港" start="20260226130000 +0800" stop="20260226135300 +0800">
		<title lang="zh">午间快线  [粤]</title>
	</programme>
	<programme channel="凤凰香港" start="20260226135300 +0800" stop="20260226135600 +0800">
		<title lang="zh">凤凰气象站 [普]</title>
	</programme>
	<programme channel="凤凰香港" start="20260226135600 +0800" stop="20260226140000 +0800">
		<title lang="zh">立法新星再出发 [粤]</title>
	</programme>
	<programme channel="凤凰香港" start="20260226140000 +0800" stop="20260226143000 +0800">
		<title lang="zh">总编辑时间  [普]</title>
	</programme>
	<programme channel="凤凰香港" start="20260226143000 +0800" stop="20260226150000 +0800">
		<title lang="zh">时事亮亮点  [普]</title>
	</programme>
	<programme channel="凤凰香港" start="20260226150000 +0800" stop="20260226153000 +0800">
		<title lang="zh">发现大湾区 [粤]</title>
	</programme>
	<programme channel="凤凰香港" start="20260226153000 +0800" stop="20260226160000 +0800">
		<title lang="zh">时事大破解  [粤]</title>
	</programme>
	<programme channel="凤凰香港" start="20260226160000 +0800" stop="20260226163000 +0800">
		<title lang="zh">凤凰大视野:暗面:战场谜案调查  [普]</title>
	</programme>
	<programme channel="凤凰香港" start="20260226163000 +0800" stop="20260226170000 +0800">
		<title lang="zh">我们和牠们  [普]</title>
	</programme>
	<programme channel="凤凰香港" start="20260226170000 +0800" stop="20260226173000 +0800">
		<title lang="zh">华润 凤凰聚焦  [普]</title>
	</programme>
	<programme channel="凤凰香港" start="20260226173000 +0800" stop="20260226180000 +0800">
		<title lang="zh">X +  [普]</title>
	</programme>
	<programme channel="凤凰香港" start="20260226180000 +0800" stop="20260226182700 +0800">
		<title lang="zh">凤凰焦点新闻 1800  [普]</title>
	</programme>
	<programme channel="凤凰香港" start="20260226182700 +0800" stop="20260226183000 +0800">
		<title lang="zh">凤凰气象站 [普]</title>
	</programme>
	<programme channel="凤凰香港" start="20260226183000 +0800" stop="20260226190000 +0800">
		<title lang="zh">以岭药业 新闻今日谈  [普]</title>
	</programme>
	<programme channel="凤凰香港" start="20260226190000 +0800" stop="20260226195700 +0800">
		<title lang="zh">全球新闻报道  [粤]</title>
	</programme>
	<programme channel="凤凰香港" start="20260226195700 +0800" stop="20260226200000 +0800">
		<title lang="zh">凤凰气象站 [普]</title>
	</programme>
	<programme channel="凤凰香港" start="20260226200000 +0800" stop="20260226202800 +0800">
		<title lang="zh">时事大破解  [粤]</title>
	</programme>
	<programme channel="凤凰香港" start="20260226202800 +0800" stop="20260226203000 +0800">
		<title lang="zh">中国银行 (香港) 直达大湾区  [粤]</title>
	</programme>
	<programme channel="凤凰香港" start="20260226203000 +0800" stop="20260226210000 +0800">
		<title lang="zh">军情观察室  [普]</title>
	</programme>
	<programme channel="凤凰香港" start="20260226210000 +0800" stop="20260226215500 +0800">
		<title lang="zh">时事直通车  [普]</title>
	</programme>
	<programme channel="凤凰香港" start="20260226215500 +0800" stop="20260226220000 +0800">
		<title lang="zh">凤凰气象站  [普]</title>
	</programme>
	<programme channel="凤凰香港" start="20260226220000 +0800" stop="20260226223000 +0800">
		<title lang="zh">晚间专线  [粤]</title>
	</programme>
	<programme channel="凤凰香港" start="20260226223000 +0800" stop="20260226230000 +0800">
		<title lang="zh">凤凰全球连线  [普]</title>
	</programme>
	<programme channel="凤凰香港" start="20260226230000 +0800" stop="20260226233000 +0800">
		<title lang="zh">总编辑时间  [普]</title>
	</programme>
	<programme channel="凤凰香港" start="20260226233000 +0800" stop="20260226235959 +0800">
		<title lang="zh">中国银行 (香港) 亚洲财经透视  [普]</title>
	</programme>
	<channel id="兵器科技">
		<display-name lang="zh">兵器科技</display-name>
	</channel>
	<programme channel="兵器科技" start="20260225001500 +0800" stop="20260225080200 +0800">
		<title lang="zh">讲武堂-2025-20</title>
	</programme>
	<programme channel="兵器科技" start="20260225080200 +0800" stop="20260225083200 +0800">
		<title lang="zh">兵工启示录-2020-48</title>
	</programme>
	<programme channel="兵器科技" start="20260225083200 +0800" stop="20260225090200 +0800">
		<title lang="zh">军火之源-2022-18</title>
	</programme>
	<programme channel="兵器科技" start="20260225090200 +0800" stop="20260225093300 +0800">
		<title lang="zh">军火之源-2022-19</title>
	</programme>
	<programme channel="兵器科技" start="20260225093300 +0800" stop="20260225100300 +0800">
		<title lang="zh">武器装备背后的故事-2019-175</title>
	</programme>
	<programme channel="兵器科技" start="20260225100300 +0800" stop="20260225103300 +0800">
		<title lang="zh">武器装备背后的故事-2019-189</title>
	</programme>
	<programme channel="兵器科技" start="20260225103300 +0800" stop="20260225112400 +0800">
		<title lang="zh">大家谈-2024-25</title>
	</programme>
	<programme channel="兵器科技" start="20260225112400 +0800" stop="20260225115000 +0800">
		<title lang="zh">军事纪实-2025-49</title>
	</programme>
	<programme channel="兵器科技" start="20260225115000 +0800" stop="20260225121500 +0800">
		<title lang="zh">军事纪实-2025-50</title>
	</programme>
	<programme channel="兵器科技" start="20260225121500 +0800" stop="20260225122200 +0800">
		<title lang="zh">魅力精品榜-2026-1</title>
	</programme>
	<programme channel="兵器科技" start="20260225122200 +0800" stop="20260225125300 +0800">
		<title lang="zh">兵工启示录-2020-49</title>
	</programme>
	<programme channel="兵器科技" start="20260225125300 +0800" stop="20260225132300 +0800">
		<title lang="zh">军火之源-2019-216</title>
	</programme>
	<programme channel="兵器科技" start="20260225132300 +0800" stop="20260225135300 +0800">
		<title lang="zh">军火之源-2019-223</title>
	</programme>
	<programme channel="兵器科技" start="20260225135300 +0800" stop="20260225142300 +0800">
		<title lang="zh">武器装备背后的故事-2020-4</title>
	</programme>
	<programme channel="兵器科技" start="20260225142300 +0800" stop="20260225145400 +0800">
		<title lang="zh">武器装备背后的故事-2020-6</title>
	</programme>
	<programme channel="兵器科技" start="20260225145400 +0800" stop="20260225154400 +0800">
		<title lang="zh">大家谈-2024-26</title>
	</programme>
	<programme channel="兵器科技" start="20260225154400 +0800" stop="20260225161000 +0800">
		<title lang="zh">军事纪实-2025-51</title>
	</programme>
	<programme channel="兵器科技" start="20260225161000 +0800" stop="20260225163600 +0800">
		<title lang="zh">军事纪实-2025-52</title>
	</programme>
	<programme channel="兵器科技" start="20260225163600 +0800" stop="20260225170600 +0800">
		<title lang="zh">兵工启示录-2020-50</title>
	</programme>
	<programme channel="兵器科技" start="20260225170600 +0800" stop="20260225173600 +0800">
		<title lang="zh">军火之源-2019-226</title>
	</programme>
	<programme channel="兵器科技" start="20260225173600 +0800" stop="20260225180700 +0800">
		<title lang="zh">军火之源-2019-230</title>
	</programme>
	<programme channel="兵器科技" start="20260225180700 +0800" stop="20260225183700 +0800">
		<title lang="zh">武器装备背后的故事-2020-7</title>
	</programme>
	<programme channel="兵器科技" start="20260225183700 +0800" stop="20260225190700 +0800">
		<title lang="zh">武器装备背后的故事-2020-8</title>
	</programme>
	<programme channel="兵器科技" start="20260225190700 +0800" stop="20260225195900 +0800">
		<title lang="zh">大家谈-2024-27</title>
	</programme>
	<programme channel="兵器科技" start="20260225195900 +0800" stop="20260225205300 +0800">
		<title lang="zh">讲武堂-2025-20</title>
	</programme>
	<programme channel="兵器科技" start="20260225205300 +0800" stop="20260225212400 +0800">
		<title lang="zh">兵工启示录-2020-51</title>
	</programme>
	<programme channel="兵器科技" start="20260225212400 +0800" stop="20260225215400 +0800">
		<title lang="zh">军火之源-2019-236</title>
	</programme>
	<programme channel="兵器科技" start="20260225215400 +0800" stop="20260225222400 +0800">
		<title lang="zh">军火之源-2019-237</title>
	</programme>
	<programme channel="兵器科技" start="20260225222400 +0800" stop="20260225225400 +0800">
		<title lang="zh">武器装备背后的故事-2020-9</title>
	</programme>
	<programme channel="兵器科技" start="20260225225400 +0800" stop="20260225232500 +0800">
		<title lang="zh">武器装备背后的故事-2019-158</title>
	</programme>
	<programme channel="兵器科技" start="20260225232500 +0800" stop="20260226001500 +0800">
		<title lang="zh">大家谈-2024-28</title>
	</programme>
	<programme channel="兵器科技" start="20260226001500 +0800" stop="20260226004200 +0800">
		<title lang="zh">军事科技-2025-18</title>
	</programme>
	<programme channel="兵器科技" start="20260226004200 +0800" stop="20260226080200 +0800">
		<title lang="zh">军事科技-2025-20</title>
	</programme>
	<programme channel="兵器科技" start="20260226080200 +0800" stop="20260226083200 +0800">
		<title lang="zh">兵工启示录-2020-49</title>
	</programme>
	<programme channel="兵器科技" start="20260226083200 +0800" stop="20260226090200 +0800">
		<title lang="zh">军火之源-2019-216</title>
	</programme>
	<programme channel="兵器科技" start="20260226090200 +0800" stop="20260226093300 +0800">
		<title lang="zh">军火之源-2019-223</title>
	</programme>
	<programme channel="兵器科技" start="20260226093300 +0800" stop="20260226100300 +0800">
		<title lang="zh">武器装备背后的故事-2020-4</title>
	</programme>
	<programme channel="兵器科技" start="20260226100300 +0800" stop="20260226103300 +0800">
		<title lang="zh">武器装备背后的故事-2020-6</title>
	</programme>
	<programme channel="兵器科技" start="20260226103300 +0800" stop="20260226112400 +0800">
		<title lang="zh">大家谈-2024-26</title>
	</programme>
	<programme channel="兵器科技" start="20260226112400 +0800" stop="20260226115000 +0800">
		<title lang="zh">军事纪实-2025-51</title>
	</programme>
	<programme channel="兵器科技" start="20260226115000 +0800" stop="20260226121500 +0800">
		<title lang="zh">军事纪实-2025-52</title>
	</programme>
	<programme channel="兵器科技" start="20260226121500 +0800" stop="20260226122200 +0800">
		<title lang="zh">魅力精品榜-2026-1</title>
	</programme>
	<programme channel="兵器科技" start="20260226122200 +0800" stop="20260226125300 +0800">
		<title lang="zh">兵工启示录-2020-50</title>
	</programme>
	<programme channel="兵器科技" start="20260226125300 +0800" stop="20260226132300 +0800">
		<title lang="zh">军火之源-2019-226</title>
	</programme>
	<programme channel="兵器科技" start="20260226132300 +0800" stop="20260226135300 +0800">
		<title lang="zh">军火之源-2019-230</title>
	</programme>
	<programme channel="兵器科技" start="20260226135300 +0800" stop="20260226142300 +0800">
		<title lang="zh">武器装备背后的故事-2020-7</title>
	</programme>
	<programme channel="兵器科技" start="20260226142300 +0800" stop="20260226145400 +0800">
		<title lang="zh">武器装备背后的故事-2020-8</title>
	</programme>
	<programme channel="兵器科技" start="20260226145400 +0800" stop="20260226154400 +0800">
		<title lang="zh">大家谈-2024-27</title>
	</programme>
	<programme channel="兵器科技" start="20260226154400 +0800" stop="20260226163900 +0800">
		<title lang="zh">讲武堂-2025-20</title>
	</programme>
	<programme channel="兵器科技" start="20260226163900 +0800" stop="20260226170900 +0800">
		<title lang="zh">兵工启示录-2020-51</title>
	</programme>
	<programme channel="兵器科技" start="20260226170900 +0800" stop="20260226173900 +0800">
		<title lang="zh">军火之源-2019-236</title>
	</programme>
	<programme channel="兵器科技" start="20260226173900 +0800" stop="20260226181000 +0800">
		<title lang="zh">军火之源-2019-237</title>
	</programme>
	<programme channel="兵器科技" start="20260226181000 +0800" stop="20260226184000 +0800">
		<title lang="zh">武器装备背后的故事-2020-9</title>
	</programme>
	<programme channel="兵器科技" start="20260226184000 +0800" stop="20260226191000 +0800">
		<title lang="zh">武器装备背后的故事-2019-158</title>
	</programme>
	<programme channel="兵器科技" start="20260226191000 +0800" stop="20260226200200 +0800">
		<title lang="zh">大家谈-2024-28</title>
	</programme>
	<programme channel="兵器科技" start="20260226200200 +0800" stop="20260226202900 +0800">
		<title lang="zh">军事科技-2025-18</title>
	</programme>
	<programme channel="兵器科技" start="20260226202900 +0800" stop="20260226205600 +0800">
		<title lang="zh">军事科技-2025-20</title>
	</programme>
	<programme channel="兵器科技" start="20260226205600 +0800" stop="20260226212700 +0800">
		<title lang="zh">兵工启示录-2020-52</title>
	</programme>
	<programme channel="兵器科技" start="20260226212700 +0800" stop="20260226215700 +0800">
		<title lang="zh">军火之源-2019-240</title>
	</programme>
	<programme channel="兵器科技" start="20260226215700 +0800" stop="20260226222700 +0800">
		<title lang="zh">军火之源-2019-243</title>
	</programme>
	<programme channel="兵器科技" start="20260226222700 +0800" stop="20260226225700 +0800">
		<title lang="zh">武器装备背后的故事-2020-17</title>
	</programme>
	<programme channel="兵器科技" start="20260226225700 +0800" stop="20260226232800 +0800">
		<title lang="zh">武器装备背后的故事-2020-21</title>
	</programme>
	<programme channel="兵器科技" start="20260226232800 +0800" stop="20260227001800 +0800">
		<title lang="zh">大家谈-2024-29</title>
	</programme>
</tv>
